Workbook

Sheet Read Me
A1: Nationwide Paid Petition Campaign Database
A3: Last verified | B3: October 24, 2026 (10 days before the Nov 3, 2026 general election)
A4: What this is | B4: Every petition project our research could find in all 50 states + DC, with status, deadlines, pay, firms and sources.
A5: Big picture | B5: Most 2026 ballot drives are finished. Live money is in the next wave: Massachusetts 2028 (first round due Nov 18 / Dec 2, 2026), Maine and Washington petitions to their legislatures, California's Jan 11, 2027 deadline, and the 2027 local / 2028 statewide cycle.
A7: STATUS KEY
A8: Confirmed active paid | B8: A current source (job ad naming the petition, finance filing, or official) shows paid circulators working it now.
A9: Strong evidence active paid | B9: Recent, credible reports of paid circulation, but not a current posting or filing.
A10: Active – paid unconfirmed | B10: The petition is collecting now, but we could not prove circulators are paid.
A11: Upcoming | B11: Announced or filed; collection hasn't started, or starts soon.
A12: Completed/Expired | B12: Drive is over. Kept because it shows who spends money and which firms they hire.
A13: No verified project | B13: We searched and found nothing verifiable. This means 'not found yet', NOT 'none exist'.
A15: TABS
A16: Database | B16: Every record. Use the filter arrows in the header row to sort by state, status, deadline, firm.
A17: Active Opportunities | B17: Live or near-live projects ranked by 5 scores (hiring, pay, deadline urgency, scale, evidence). Total = formula.
A18: State Coverage | B18: One row per state with live counts (formulas) so you can see where activity is and where gaps remain.
A19: Firms | B19: Circulation companies found, their states, contacts and pay.
A20: Job Postings | B20: Recent circulator job ads with stated pay.
A21: Trends & Laws | B21: Industry notes: pay rates, new laws, where the market is moving.
A22: New Discoveries | B22: Monitoring log. Add each newly found project here first, then move it to Database once verified.
A24: RULES WE FOLLOWED | B24: Nothing invented. 'unknown' means no reliable public source. A registered petition is NOT counted as paid. Contacts are official public business contacts only.
A25: Known gaps | B25: Several state election sites and campaign-finance systems blocked automated access (e.g. Florida initiative database, Nevada SOS, Missouri SOS 2028 page, Arizona filings). Those are the first places to check by hand.
A30: Today (edit to refresh 'Days Left') | B30: 46319

Sheet Database
A1: ID | B1: State | C1: Region | D1: Area | E1: Campaign / Petition | F1: Purpose | G1: Type | H1: Sponsor / Committee | I1: Circulation Firm | J1: Status | K1: Signatures Required | L1: Deadline | M1: Deadline (date) | N1: Days Left | O1: Signatures Collected | P1: Circulator Pay | Q1: Hiring Link | R1: Budget / Spend | S1: Decision Maker | T1: Public Contact | U1: Website | V1: Evidence Note | W1: Source 1 | X1: Source 2 | Y1: Source 3 | Z1: More Sources | AA1: Discovery Batch | AB1: Last Verified
A2: P001 | B2: Alabama | C2: Southeast | D2: Statewide | E2: Local recall/referendum/charter petitions | F2: Party/independent ballot access (Alabama has no statewide citizen initiative) | G2: Candidate/party ballot access | H2: unknown | I2: unknown | J2: No verified project | K2: 42,459 for party or statewide independent (2026) | L2: May 19, 2026 (statewide). The U.S. House deadline moved to Aug 11, 2026 for CD 1, 2, 6 and 7 (passed). | M2: 46161 | N2: =IF(M2="","",M2-'Read Me'!$B$30) -> -158 | O2: unknown | P2: unknown | Q2: unknown | R2: unknown | S2: unknown | T2: unknown | U2: unknown | V2: Checked Ballot Access News June 2026 only. Singleton v. Allen (May 26) struck the new districts. No verified paid petition activity. The search budget ran out before local petitions and job boards could be checked. | W2: https://ballot-access.org/2026/06/22/june-2026-ballot-access-news-print-edition/ | AA2: Pass 1 + Pass 2 | AB2: 46319
A3: P002 | B3: Alaska | C3: West | D3: Statewide | E3: Proposed initiative requiring state/federal candidates to gather signatures before running | F3: Require candidates for state and federal office in Alaska to gather petition signatures to get on the ballot | G3: Statutory initiative (application stage; likely 2028 target) | H3: unknown | I3: unknown | J3: Upcoming | K3: unknown | L3: unknown | N3: =IF(M3="","",M3-'Read Me'!$B$30) | O3: unknown | P3: unknown | Q3: unknown | R3: unknown | S3: unknown | T3: unknown | U3: unknown | V3: Known only from the ADN headline (10/14/26); the article could not be fetched because robots.txt blocks it. Sponsors and status unverified. | W3: https://www.adn.com/politics/2026/10/14/proposed-ballot-initiative-would-require-alaska-federal-state-candidates-to-gather-signatures-before-running-for-office/ | AA3: Pass 1 | AB3: 46319
A4: P003 | B4: Alaska | C4: West | D4: Statewide | E4: 25ANMA - Alaska Natural Medicine Act | F4: Regulated natural medicine (psychedelics) program; decriminalize personal use for adults 21+ | G4: Statutory initiative | H4: Natural Alaska Medicine Inc. (nonprofit) | I4: unknown | J4: Completed/Expired | K4: 10% of voters in last general election, from at least 30 of 40 House districts (exact number unknown) | L4: Booklet filing deadline 2026-09-14 (passed) | M4: 46279 | N4: =IF(M4="","",M4-'Read Me'!$B$30) -> -40 | O4: unknown | P4: unknown | Q4: unknown | R4: unknown | S4: unknown | T4: unknown | U4: https://www.elections.alaska.gov/petitions-and-ballot-measures/petition-status/petition_id/gr8j9 | V4: Circulation window ended 9/14/26. Whether booklets were filed or signatures are under review is unknown. | W4: https://www.elections.alaska.gov/petitions-and-ballot-measures/ | X4: https://alaskabeacon.com/briefs/ballot-initiative-to-decriminalize-psychedelics-in-alaska-cleared-for-signature-gathering/ | AA4: Pass 1 | AB4: 46319
A5: P004 | B5: Alaska | C5: West | D5: Statewide | E5: 25USCV - Only U.S. citizens may be qualified voters | F5: Amend AS 15.05.010 to state explicitly that only U.S. citizens meeting listed requirements may vote | G5: Statutory initiative | H5: unknown | I5: unknown | J5: Completed/Expired | K5: 34,098 across 30 House districts | L5: Properly filed 2026-03-17; Nov 3, 2026 ballot unless legislature acts | M5: 46098 | N5: =IF(M5="","",M5-'Read Me'!$B$30) -> -221 | O5: 34,944 qualified across 40 House districts | P5: unknown | Q5: unknown | R5: unknown | S5: unknown | T5: unknown | U5: https://www.elections.alaska.gov/petitions-and-ballot-measures/ | V5: Certified 3/17/26. The AK petitions page still lists it as 'booklets circulating' with a 10/29/26 booklet deadline, which conflicts with the certification release and looks stale. | W5: https://www.elections.alaska.gov/lieutenant-governor-nancy-dahlstrom-certifies-proper-filing-of-ballot-initiative-petition-25uscv/ | X5: https://www.elections.alaska.gov/petitions-and-ballot-measures/ | AA5: Pass 1 | AB5: 46319
A6: P005 | B6: Arizona | C6: Mountain/Southwest | D6: City of Scottsdale | E6: Axon headquarters / apartments zoning referendum | F6: Refer the city council's November 2024 approval of Axon's HQ campus and apartments to voters | G6: Municipal referendum | H6: Taxpayers Against Awful Apartment Zoning Exemptions (TAAAZE); signature drive described as union-linked | I6: unknown | J6: Completed/Expired | K6: unknown (city clerk certified it met the constitutional minimum) | L6: Filed December 2024; certified January 30, 2025 | M6: 45687 | N6: =IF(M6="","",M6-'Read Me'!$B$30) -> -632 | O6: More than 26,000 | P6: unknown | Q6: unknown | R6: unknown | S6: unknown | T6: unknown | U6: https://www.scottsdaleaz.gov/elections/referendum | V6: Shows local referendum demand in Arizona. A state bill was moving to cancel the vote; whether it reached the November 2026 ballot was not verified. | W6: https://www.abc15.com/news/business/axon-headquarters-referendum-certified-by-city-of-scottsdale | X6: https://www.yahoo.com/news/collecting-26-000-signatures-scottsdale-195209122.html | AA6: Pass 1 | AB6: 46319
A7: P006 | B7: Arizona | C7: Mountain/Southwest | D7: Statewide | E7: Protect the Vote Arizona (constitutional right to early and mail-in voting) | F7: Put early and mail voting into the Arizona Constitution | G7: Statewide constitutional amendment initiative | H7: Protect the Vote Arizona (funded largely by United Food and Commercial Workers and other unions, per KJZZ) | I7: unknown (Lumen Strategies managed the campaign; Lumen is a PR/consulting firm, not confirmed as the signature vendor) | J7: Completed/Expired | K7: 383,923 valid | L7: July 2, 2026 (campaign chose not to file) | M7: 46205 | N7: =IF(M7="","",M7-'Read Me'!$B$30) -> -114 | O7: About 439,000 gathered, not submitted | P7: unknown | Q7: unknown | R7: unknown | S7: Stacy Pearson (spokesperson; Lumen Strategies co-founder) | T7: unknown | U7: unknown | V7: Dropped because the expected validity rate was too low. Arizona Agenda said the drive was 'largely undertaken by volunteers' (about 1,700 circulators). It is a possible 2028 refile, but no source mentions 2028 plans. | W7: https://www.kjzz.org/elections/2026-07-02/arizona-group-drops-petition-to-enshrine-early-voting-in-the-state-constitution | X7: https://www.arizonaagenda.com/p/protect-the-vote-s-final-push | AA7: Pass 1 | AB7: 46319
A8: P007 | B8: Arizona | C8: Mountain/Southwest | D8: Statewide | E8: Protect Education, Accountability Now (ESA limits) | F8: Limit Empowerment Scholarship Account eligibility to families earning under $150,000 (starting 2027-28) and bar luxury purchases and paying family members | G8: Statewide initiated statute | H8: Protect Education, Accountability Now campaign (endorsed by Arizona Education Association and Save Our Schools Arizona) | I8: unknown | J8: Completed/Expired | K8: 255,949 valid | L8: July 2, 2026 (submitted) | M8: 46205 | N8: =IF(M8="","",M8-'Read Me'!$B$30) -> -114 | O8: 421,451 submitted | P8: unknown | Q8: unknown | R8: unknown | S8: unknown | T8: unknown | U8: unknown | V8: Only one of six 2026 Arizona initiatives filed signatures. No firm named in the source. A 400K+ drive in Arizona almost always uses paid circulators, but no source here confirms it. Check the AZ SOS paid-circulator registry or SeeTheMoney to see who was paid. | W8: https://news.ballotpedia.org/2026/07/07/arizona-campaign-submits-421451-signatures-for-initiative-to-limit-empowerment-scholarship-account-eligibility-and-spending/ | AA8: Pass 1 + Pass 2 | AB8: 46319
A9: P008 | B9: Arizona | C9: South | D9: Benson (Cochise County) | E9: Benson recall - Mayor Joe Konrad and 4 council members | F9: Recall city officials | G9: Municipal recall | H9: Committee for a Better Benson | I9: unknown | J9: Completed/Expired | K9: Konrad 327; Johnson 301; Boyle, Hayes, Maldonado 267 each | L9: Petitions submitted Oct 29 2025 | M9: 45959 | N9: =IF(M9="","",M9-'Read Me'!$B$30) -> -360 | O9: unknown | P9: unknown | Q9: unknown | R9: unknown | S9: unknown | T9: unknown | U9: unknown | V9: Follow-up headline indicates the Konrad recall 'fell short for common petition issues' (article body not fetched). No active AZ recall verified. | W9: https://www.myheraldreview.com/news/benson/recall-effort-could-oust-benson-mayor-and-4-of-6-council-members/article_c4e47701-9375-4059-90af-f546cb7905ba.amp.html | X9: https://www.myheraldreview.com/news/benson/konrad-recall-effort-fell-short-for-common-petition-issues/article_b2a9d91b-bf7d-4406-98cc-26ee613abe78.amp.html | AA9: Pass 2 (gap-fill) | AB9: 46319
A10: P009 | B10: Arizona | C10: South | D10: Phoenix | E10: Right-Size Consulting paid petition canvassing program | F10: Petition signature collection (campaign not named) | G10: unknown | H10: unknown | I10: Right-Size Consulting | J10: Completed/Expired | K10: unknown | L10: unknown | N10: =IF(M10="","",M10-'Read Me'!$B$30) | O10: unknown | P10: $20/hour | Q10: https://careers.arena.run/companies/job-post-2/jobs/68651818-right-size-consulting-canvasser | R10: unknown | S10: unknown | T10: email listed on posting (obfuscated in fetch) | U10: unknown | V10: Posted Feb 25 2026, before the July 2 2026 AZ filing deadline; likely tied to 2026 cycle. Current status unknown. | W10: https://careers.arena.run/companies/job-post-2/jobs/68651818-right-size-consulting-canvasser | AA10: Pass 2 (gap-fill) | AB10: 46319
A11: P010 | B11: Arkansas | C11: Plains/Texas | D11: Statewide | E11: Protect AR Rights – Ballot Measure Rights Amendment | F11: Constitutional amendment protecting the right to initiative/referendum; bar the legislature from amending or repealing citizen amendments | G11: Statewide constitutional initiative, 2026 | H11: Protect AR Rights (ballot question committee; member org Arkansas Public Policy Panel, Exec. Dir. Bill Kopsky) | I11: unknown | J11: Completed/Expired | K11: 90,704 verified | L11: July 3, 2026 (submitted) | M11: 46206 | N11: =IF(M11="","",M11-'Read Me'!$B$30) -> -113 | O11: 108,837 submitted | P11: unknown | Q11: unknown | R11: unknown | S11: Bill Kopsky (Arkansas Public Policy Panel) | T11: unknown | U11: unknown | V11: The AR SOS page lists 'None' citizen-initiated measures for the 2026 general election, so this measure apparently did not qualify (reason not found). A federal judgment (WD Ark., Aug 21, 2026) struck down some Arkansas initiative restrictions. No 2028 AG-certified ballot titles were found, and the paid canvasser registration list was not checked. | W11: https://news.ballotpedia.org/2026/07/08/signatures-submitted-for-arkansas-initiative-to-prohibit-the-state-legislature-from-amending-or-repealing-constitutional-amendments-and-require-voter-approval-for-changes-to-the-initiative-and-referen/ | X11: https://arkansasadvocate.com/2025/07/28/arkansas-attorney-general-approves-second-direct-democracy-ballot-title/ | Y11: https://www.sos.arkansas.gov/elections/initiatives-and-referenda | AA11: Pass 1 | AB11: 46319
A12: P011 | B12: California | C12: West | D12: Statewide | E12: Repeal Top-Two Open Primary (SOS #2022 / AG 26-0004) | F12: Repeal California's top-two open primary system adopted by voters in 2010 | G12: Initiative constitutional amendment (Nov 7, 2028 ballot) | H12: Proponent: Steven Maviglio (Democratic consultant). Supporters named by proponent include California Labor Federation, Greens, Carl DeMaio, a former Republican Party chair | I12: unknown | J12: Active – paid unconfirmed | K12: 874,641 valid | L12: 2027-01-11 (end of 180-day circulation period; submit to county elections officials) | M12: 46398 | N12: =IF(M12="","",M12-'Read Me'!$B$30) -> 79 | O12: unknown (CA SOS 25%-signature list showed 'None at this time' when checked) | P12: unknown | Q12: unknown | R12: unknown (no committee appeared on FPPC pending/circulating top-contributor lists checked) | S12: Steven Maviglio (proponent of record) | T12: Proponent email published by CA SOS: steven.maviglio@gmail.com | U12: undothetoptwo.com | V12: Only CA statewide initiative still in circulation (cleared 7/14/26, deadline 1/11/27). Needing ~875k valid signatures in 180 days normally implies paid circulation, but no source found confirming a firm, pay rate or committee spending. Check Cal-Access for the committee's payments to petition firms. No 25% report filed as of check. | W12: https://www.sos.ca.gov/administration/news-releases-and-advisories/2026-news-releases-and-advisories/proposed-initiative-enters-circulation-repeals-top-two-open-primary-election-process-initiative-constitutional-amendment | X12: https://www.kpbs.org/news/politics/2026/07/16/effort-to-repeal-californias-top-two-jungle-primary-system-is-closer-to-qualifying-for-the-2028-ballot | Y12: https://ivn.us/more-choice-california-launches-to-defend-nonpartisan-primary-as-democratic-and-republican-operatives-quietly-join-forces-to-repeal-it-2026-05-13/ | Z12: https://fox5sandiego.com/news/no-more-jungle-primary-a-new-initiative-would-end-californias-top-two-system/amp/; https://www.fppc.ca.gov/transparency/top-contributors/nov-26-gen/pending-circulating-ballot-measures.html; https://sos.ca.gov/elections/ballot-measures/initiative-and-referendum-status/initiatives-referenda-cleared-circulation; https://sos.ca.gov/elections/ballot-measures/initiative-and-referendum-status/circulating-initiatives-25percent-signatures; https://ballot-access.org/?p=93674 | AA12: Pass 1 + Pass 2 | AB12: 46319
A13: P012 | B13: California | C13: West | D13: Statewide | E13: Exempts Additional Food Products from State and Local Sales Taxes (SOS #2023 / AG 26-0005) | F13: Constitutional amendment expanding sales-tax exemption for food products | G13: Initiative constitutional amendment | H13: John Pimentel (proponent) | I13: unknown | J13: Active – paid unconfirmed | K13: 874,641 valid | L13: 2027-03-24 | M13: 46470 | N13: =IF(M13="","",M13-'Read Me'!$B$30) -> 151 | O13: unknown | P13: unknown | Q13: unknown | R13: unknown | S13: John Pimentel | T13: John Pimentel, 20 Park Road, Burlingame, CA 94010; (650) 269-8933; John@JohnPimentel.com (per CA SOS release PR26-122) | U13: unknown | V13: Entered circulation Sept 25, 2026. It is the newest CA statewide initiative in circulation, per the SOS 2026 release index. No funding committee, firm or signature drive activity was found. A proponent with no visible funding is a possible client for a feasibility or full-campaign pitch. | W13: https://www.sos.ca.gov/administration/news-releases-and-advisories/2026-news-releases-and-advisories/california-secretary-state-shirley-n-weber-phd-announces-proposed-initiative-has-entered-circulation-exempts-additional-food-pro | X13: https://www.sos.ca.gov/administration/news-releases-and-advisories/2026-news-releases-and-advisories | AA13: Pass 2 (gap-fill) | AB13: 46319
A14: P013 | B14: California | C14: West | D14: Los Angeles and surrounding areas | E14: Urban Signers LLC - Signature Collector (unnamed petition projects) | F14: Paid signature collection for unnamed 'official petition and local campaign projects' | G14: unknown (local/official petitions, unspecified) | H14: unknown | I14: Urban Signers LLC | J14: Active – paid unconfirmed | K14: unknown | L14: unknown | N14: =IF(M14="","",M14-'Read Me'!$B$30) | O14: unknown | P14: $5 or $10 per signature depending on project; advertised $200-$1,000/day; paid weekly or bi-weekly | Q14: https://urban-signers-llc.careerplug.com/jobs/3365854 | R14: unknown | S14: unknown | T14: Apply via CareerPlug form only; no phone/email listed | U14: https://urban-signers-llc.careerplug.com/jobs/3365854 | V14: Paid job ad; page metadata updated 2026-10-16 (original post date unknown). Names no specific petition, and the only statewide CA petition circulating is the top-two repeal, so which projects are active is unverified. | W14: https://urban-signers-llc.careerplug.com/jobs/3365854 | AA14: Pass 1 | AB14: 46319
A15: P014 | B15: California | C15: West | D15: Statewide | E15: Prohibit use after 2026 of Prop 50 temporary congressional maps (AG 25-0031) | F15: Constitutional amendment ending the 2025 voter-adopted temporary congressional maps after 2026 | G15: Initiative constitutional amendment | H15: James V. Lacy (proponent) | I15: unknown | J15: Completed/Expired | K15: 874,641 valid | L15: 2026-07-13 | M15: 46216 | N15: =IF(M15="","",M15-'Read Me'!$B$30) -> -103 | O15: unknown | P15: unknown | Q15: unknown | R15: unknown | S15: James V. Lacy | T15: c/o Bradley W. Hertz, Esq., 22815 Ventura Blvd #405, Los Angeles, CA 91364; (818) 593-2949; brad@bradleyhertzlaw.com (per CA SOS release PR26-08) | U15: unknown | V15: The circulation window has closed and the outcome was not verified. | W15: https://www.sos.ca.gov/administration/news-releases-and-advisories/2026-news-releases-and-advisories/proposed-initiative-enters-circulation-prohibits-use-after-2026-temporary-congressional-district-maps-adopted-voters-2025-respon | AA15: Pass 2 (gap-fill) | AB15: 46319
A16: P015 | B16: California | C16: West | D16: Statewide | E16: Exempts Homeowners 60+ from Property Taxes (AG 25-0035) | F16: Constitutional amendment exempting certain homeowners aged 60+ from property taxes | G16: Initiative constitutional amendment | H16: Rishi Kumar (proponent) | I16: unknown | J16: Completed/Expired | K16: 874,641 valid | L16: 2026-08-04 | M16: 46238 | N16: =IF(M16="","",M16-'Read Me'!$B$30) -> -81 | O16: unknown | P16: unknown | Q16: unknown | R16: unknown | S16: Rishi Kumar | T16: P.O. Box 110484, Campbell, CA 95011; (408) 805-5993; VoteRishiKumar@gmail.com (per CA SOS release PR26-21) | U16: unknown | V16: The circulation window has closed. Whether signatures were submitted is unknown. The proponent could refile for 2028. | W16: https://www.sos.ca.gov/administration/news-releases-and-advisories/2026-news-releases-and-advisories/proposed-initiative-enters-circulation-exempts-certain-homeowners-aged-60-or-older-property-taxes-initiative-constitutional-amen | AA16: Pass 2 (gap-fill) | AB16: 46319
A17: P016 | B17: California | C17: West | D17: Statewide | E17: Changes Ballot Initiative Procedures and Elections (AG 26-0001/26-0002; SOS #2019/#2020) | F17: Change ballot initiative procedures and elections (constitutional amendment and statute) | G17: Initiative constitutional amendment and statute | H17: Thomas Jefferson Cares (proponent) | I17: unknown | J17: Completed/Expired | K17: 874,641 valid | L17: 2026-10-05 (passed) | M17: 46300 | N17: =IF(M17="","",M17-'Read Me'!$B$30) -> -19 | O17: unknown (no 25% report on SOS list) | P17: unknown | Q17: unknown | R17: unknown | S17: Thomas Jefferson Cares (proponent) | T17: 12816 Inglewood Ave #383, Hawthorne, CA 90250; (310) 929-0260; Tom@UH.do (as published by CA SOS) | U17: unknown | V17: Circulation deadline passed 10/5/26. No evidence of paid circulation or a 25% signature report, so it almost certainly did not qualify. | W17: https://www.sos.ca.gov/administration/news-releases-and-advisories/2026-news-releases-and-advisories/california-secretary-state-shirley-n-weber-phd-announces-proposed-initiative-has-entered-circulation-changes-ballot-initiative-p | X17: https://sos.ca.gov/elections/ballot-measures/initiative-and-referendum-status/initiatives-referenda-cleared-circulation | AA17: Pass 1 | AB17: 46319
A18: P017 | B18: California | C18: West | D18: Statewide | E18: Changes Ballot Initiative Procedures (AG 26-0001) and California Strategic Implementation Board (AG 26-0003) | F18: Create a California Strategic Implementation Board to change numerous aspects of state law and government | G18: Initiative constitutional amendment | H18: Thomas Jefferson Cares (proponent) | I18: unknown | J18: Completed/Expired | K18: 874,641 valid | L18: 2026-10-13 (passed) | M18: 46308 | N18: =IF(M18="","",M18-'Read Me'!$B$30) -> -11 | O18: unknown (no 25% report on SOS list) | P18: unknown | Q18: unknown | R18: unknown | S18: Thomas Jefferson Cares (proponent) | T18: (310) 929-0260; Tom@UH.do (proponent contact CA SOS published for this proponent's related measure) | U18: unknown | V18: Circulation deadline passed 10/13/26; no signs of a paid drive. The SOS cleared-for-circulation list also shows a fourth entry with this same title under Steven Maviglio (SOS #2022, deadline 1/11/27), but the SOS press release for #2022 gives the top-two repeal title. Likely a listing error; the top-two record above relies on the press release. | W18: https://www.sos.ca.gov/administration/news-releases-and-advisories/2026-news-releases-and-advisories/california-secretary-state-shirley-n-weber-phd-announces-proposed-initiative-has-entered-circulation-changes-ballot-initiative-p | X18: https://www.sos.ca.gov/administration/news-releases-and-advisories/2026-news-releases-and-advisories/california-secretary-state-shirley-n-weber-phd-announces-proposed-initiative-has-entered-circulation | Y18: https://sos.ca.gov/elections/ballot-measures/initiative-and-referendum-status/initiatives-referenda-cleared-circulation | AA18: Pass 1 + Pass 2 | AB18: 46319
A19: P018 | B19: California | C19: West | D19: Statewide | E19: CA per-signature pay benchmark - Billionaire Tax and counter-measure (2026 cycle) | F19: Market pay-rate evidence for CA paid circulators | G19: Initiative (statewide) | H19: Billionaire Tax Act supporters; the counter-measure was backed by Sergey Brin among others | I19: unknown (data cited from consulting firm Bicker, Castillo, Fairbanks & Spitz) | J19: Completed/Expired | K19: unknown | L19: Completed (2026 cycle) | N19: =IF(M19="","",M19-'Read Me'!$B$30) | O19: unknown | P19: $12 per signature (billionaire tax, up from $4 in fall 2025); $15 per signature (counter-measure), as of late Feb 2026 | Q19: unknown | R19: unknown | S19: unknown | T19: unknown | U19: unknown | V19: This is pay-rate context, not an open job. No current (Oct 2026) CA circulator job ad with a stated pay rate was verified: a Craigslist WA ad and a JobsInGovernment Carter Consulting ad could not be retrieved. | W19: https://sfstandard.com/2026/03/05/california-ballot-bounties-have-gone-wild/ | AA19: Pass 2 (gap-fill) | AB19: 46319
A20: P019 | B20: California | C20: West | D20: Los Angeles (Van Nuys, Koreatown, NE LA, South LA) | E20: The Outreach Team - LA petitioners (corporate accountability initiative + LA Fire Department expansion initiative) | F20: Signature gathering for two LA ballot initiatives: hold large corporations accountable/reinvest in communities; expand the LA Fire Department | G20: Local (City of Los Angeles) ballot initiatives | H20: unknown | I20: The Outreach Team | J20: Completed/Expired | K20: unknown | L20: Job posting closed 2026-05-19 | M20: 46161 | N20: =IF(M20="","",M20-'Read Me'!$B$30) -> -158 | O20: unknown | P20: $27/hr base, $28/hr leads, $20-$150 daily bonuses, +$2/hr bilingual, overtime, referral bonuses | Q20: https://www.theoutreachteam.net/interest-form-tot | R20: unknown | S20: unknown | T20: https://www.theoutreachteam.net/interest-form-tot | U20: https://www.theoutreachteam.net | V20: Confirmed paid hourly drive but expired (closed 5/19/26). Useful because The Outreach Team is an hourly-pay firm active in LA local measures. Measure outcomes not checked. | W20: https://la2050.org/job/the-outreach-team-petitioners-make-a-difference-dollars-27-dollars-28-hr-bonuses | AA20: Pass 1 | AB20: 46319
A21: P020 | B21: California | C21: West | D21: City of San Diego | E21: Balboa Park Free Parking Restoration Act / Trash fee repeal petitions | F21: Repeal Balboa Park paid parking and the city trash fee | G21: Municipal initiative (with council-rehear threshold) | H21: Richard Bailey (Balboa Park measure); San Diego United Communities (Margaret Virissimo) | I21: unknown | J21: Completed/Expired | K21: About 81,000-82,000 verified for the ballot; about 24,000-24,500 to force a council rehearing | L21: June 2026 (exact date unknown) | N21: =IF(M21="","",M21-'Read Me'!$B$30) | O21: unknown | P21: unknown | Q21: unknown | R21: unknown | S21: Richard Bailey; Margaret Virissimo | T21: unknown | U21: repealthefees.com | V21: Volunteer drives that targeted the Nov 2026 ballot. The deadlines have passed and outcomes were not verified. Fee disputes like these show local demand that could recur. | W21: https://timesofsandiego.com/politics/2026/04/05/petition-to-repeal-parking-fees-at-balboa-park-cleared-to-gather-signatures/ | X21: https://www.10news.com/news/local-news/san-diego-petition-drive-targets-trash-fee-balboa-park-parking-charges-on-mothers-day | AA21: Pass 2 (gap-fill) | AB21: 46319
A22: P021 | B22: California | C22: West | D22: Statewide | E22: UC support staff first-time homebuyer down payment loan program initiative | F22: Require UC to create a down payment loan program (20% of home value) for eligible UC support staff | G22: Initiative constitutional amendment (qualified for Nov 7, 2028 ballot) | H22: AFSCME Local 3299 | I22: unknown | J22: Completed/Expired | K22: 874,641 valid | L22: Qualified 2026-10-02; withdrawal deadline 2028-06-29 | M22: 46297 | N22: =IF(M22="","",M22-'Read Me'!$B$30) -> -22 | O22: 1,265,569 raw submitted; 947,631 valid (full count) | P22: unknown | Q22: unknown | R22: unknown | S22: AFSCME 3299 (sponsor) | T22: unknown | U22: unknown | V22: First initiative qualified for CA 2028 ballot. Drive is finished; useful as a sign that AFSCME 3299 runs large signature drives. Firm and spending not reported in source; check Cal-Access. | W22: https://news.ballotpedia.org/2026/10/06/first-initiative-qualifies-for-the-2028-ballot-in-california/ | AA22: Pass 1 | AB22: 46319
A23: P022 | B23: Colorado | C23: Mountain/Southwest | D23: Colorado Springs and Denver | E23: 2027 municipal elections - candidate nominating petitions (Colorado Springs Apr 6, 2027; Denver 2027 municipal) | F23: Candidate petitions for Colorado Springs Mayor and 3 At-Large Council seats, plus district seats; Denver 2027 municipal candidate petitions of nomination | G23: Candidate ballot access petition | H23: Individual candidates (not yet known) | I23: unknown | J23: Upcoming | K23: unknown | L23: Colorado Springs candidate filing Jan 4-25, 2027; Denver deadline per the 2027 candidate packet (not read in detail) | M23: 46391 | N23: =IF(M23="","",M23-'Read Me'!$B$30) -> 72 | O23: unknown | P23: unknown | Q23: unknown | R23: unknown | S23: Candidates (TBD) | T23: Colorado Springs City Clerk; Denver Clerk and Recorder Elections Division | U23: https://mayor.coloradosprings.gov/city-clerk/page/candidate-and-campaign-information | V23: This is a real upcoming petition window. Paid circulation is NOT confirmed; municipal candidate petitions are often volunteer-gathered. Also, Colorado's 2027-28 statewide title board list could not be read (the SOS 2027-2028 filings page was blocked), so statewide 2028 filings are unverified. Any paid entity must be licensed by the CO SOS and its circulators must wear 'PAID CIRCULATOR' badges. | W23: https://mayor.coloradosprings.gov/city-clerk/page/candidate-and-campaign-information | X23: https://www.denvergov.org/files/assets/public/v/1/clerk-and-recorder/documents/elections/guides/2027-municipal-candidate-information-packet-pdf-version.pdf | AA23: Pass 1 | AB23: 46319
A24: P023 | B24: Colorado | C24: Mountain/Southwest | D24: Statewide | E24: Protect Kids Colorado Initiatives #108, #109, #110 (now Propositions 133, 134, 135) | F24: #108 life sentence for child sex trafficking; #109 restrict transgender students in sports; #110 ban certain gender-affirming procedures for minors | G24: Statewide initiated statutes | H24: Protect Kids Colorado (Executive Director Erin Lee; founder Kevin Lundberg); Protect our Children Issue Committee for fundraising | I24: Taylor Petition Management (Tracy Taylor), registered with the state for #108-110 | J24: Completed/Expired | K24: 124,238 valid each | L24: #108 Feb 16, 2026; #109 and #110 Feb 20, 2026 (all submitted by Feb 20) | M24: 46069 | N24: =IF(M24="","",M24-'Read Me'!$B$30) -> -250 | O24: Group said more than 170,000 submitted for each | P24: unknown | Q24: unknown | R24: unknown | S24: Erin Lee (Executive Director); Michele Austin (proponent/strategist) | T24: unknown | U24: https://protectkidscolorado.org | V24: Confirmed paid by the end: the drive switched from volunteers to a licensed paid petition entity (Taylor Petition Management), and all three qualified as Props 133-135. Proves Taylor Petition Management is active in Colorado. | W24: https://coloradotimesrecorder.com/2026/02/activists-now-paying-for-signatures-for-anti-trans-ballot-measures/76656/ | X24: https://completecolorado.com/2025/09/05/ballot-measures-protecting-kids-signature-gathering/ | Y24: https://kiowacountypress.net/content/14-measures-will-appear-colorados-statewide-ballot-2026 | AA24: Pass 1 | AB24: 46319
A25: P024 | B25: Colorado | C25: Mountain/Southwest | D25: Statewide | E25: Initiative 177 - right to buy and use natural gas for cooking and heating | F25: Constitutional right to purchase and sell natural gas for homes and businesses | G25: Statewide constitutional initiative | H25: Advance Colorado; funders for signatures Colorado Dawn and A Common Sense America | I25: unknown | J25: Completed/Expired | K25: 124,238 valid | L25: Filed June 24, 2026; verification due by Aug 21, 2026 | M25: 46197 | N25: =IF(M25="","",M25-'Read Me'!$B$30) -> -122 | O25: unknown | P25: unknown | Q25: unknown | R25: Colorado Dawn $750,000 for signatures; A Common Sense America $625,000 to help collect signatures (per KUNC) | S25: unknown | T25: unknown | U25: unknown | V25: About $1.375M was earmarked for signatures, which is strong evidence of paid circulation. Advance Colorado is linked to 6 of the 13 citizen initiatives on the 2026 CO ballot (Amendments 81, 82, 85, 86 and Props 132, 136), making it the largest repeat buyer of petition work in the region. KUNC puts the cost at $1M-$3M per measure. Firm names are in the CO SOS paid-circulator reports and TRACER, which were not read. | W25: https://news.ballotpedia.org/2026/06/26/signatures-submitted-for-colorado-initiative-for-the-right-to-purchase-and-sell-natural-gas-for-cooking-and-heating-in-homes-or-businesses/ | X25: https://www.kunc.org/politics/2026-08-21/colorado-ballot-questions-meant-to-keep-special-interests-in-check-are-increasingly-created-by-them | AA25: Pass 1 | AB25: 46319
A26: P025 | B26: Colorado | C26: Mountain/Southwest | D26: City and County of Denver | E26: Denver force-feeding / foie gras ban initiated ordinance | F26: Ban force-feeding birds and the sale of force-fed products in Denver | G26: Municipal initiated ordinance | H26: Pro-Animal Colorado | I26: unknown | J26: Completed/Expired | K26: unknown | L26: Nov 3, 2026 ballot | M26: 46329 | N26: =IF(M26="","",M26-'Read Me'!$B$30) -> 10 | O26: unknown | P26: unknown | Q26: unknown | R26: unknown | S26: unknown | T26: unknown | U26: unknown | V26: The only citizen-initiated Denver measure for Nov 2026 per Brownstein. Whether circulators were paid or volunteers is unknown. | W26: https://www.bhfs.com/insight/denvers-2026-ballot-takes-shape-key-initiatives-and-the-at-large-city-council-vacancy-election/ | X26: https://www.denvergov.org/files/assets/public/v/1/clerk-and-recorder/documents/elections-division/2025/measures/force-feeding-sample-petition-stapled-copy-with-blue-manuscript.pdf | AA26: Pass 1 | AB26: 46319
A27: P026 | B27: Colorado | C27: Mountain/Southwest | D27: Denver metro and Colorado Springs | E27: Landslide Political - candidate signature gathering and canvassing (Colorado) | F27: Signature gathering to qualify 2026 candidates for the Colorado ballot, plus door-to-door canvassing | G27: Candidate ballot access petition / canvass | H27: Unnamed 2026 candidates | I27: Landslide Political | J27: Completed/Expired | K27: unknown | L27: unknown | N27: =IF(M27="","",M27-'Read Me'!$B$30) | O27: unknown | P27: $25/hour ($150 per 6-hour shift), paid weekly | Q27: https://landslidepolitical.recruitee.com/o/canvasser-hiring-immediately-denver-metro-area-25hr | R27: unknown | S27: unknown | T27: Apply via the Recruitee posting; no phone or email listed | U27: https://landslidepolitical.recruitee.com | V27: The posting is still live but undated and refers to 2026 ballot qualification, which is over. Landslide keeps standing postings, so it could re-staff for 2027 municipal or 2028 work. That is unconfirmed. | W27: https://landslidepolitical.recruitee.com/o/canvasser-hiring-immediately-denver-metro-area-25hr | X27: https://landslidepolitical.recruitee.com/o/canvasser-hiring-immediately-colorado-springs-25hr | AA27: Pass 1 | AB27: 46319
A28: P027 | B28: Colorado | C28: Mountain/Southwest | D28: Colorado Springs | E28: Killin for Colorado - candidate ballot-access petition | F28: Collect signatures to put a Democratic candidate on the 2026 ballot | G28: Candidate ballot access petition | H28: Killin for Colorado (candidate committee) | I28: 503 Strategies (recruiting contact domain) | J28: Completed/Expired | K28: unknown | L28: unknown (2026 candidate petition period is over) | N28: =IF(M28="","",M28-'Read Me'!$B$30) | O28: unknown | P28: $30/hour, 10-30 hrs/week | Q28: https://jobs.arena.run/jobs/paid-petition-circulator-reci-b-ea-nzesly5-h-kl/ | R28: unknown | S28: unknown | T28: annika@503-strategies.com (from job posting) | U28: unknown | V28: The job posting confirms a paid circulator role, but it is undated and tied to the 2026 ballot, so it has expired. It shows 503 Strategies does paid candidate petitioning in Colorado. | W28: https://jobs.arena.run/jobs/paid-petition-circulator-reci-b-ea-nzesly5-h-kl/ | X28: https://careers.arena.run/companies/job-post-2/jobs/64551809-killin-for-colorado-paid-petition-circulator | AA28: Pass 1 | AB28: 46319
A29: P028 | B29: Connecticut | C29: Northeast | D29: Statewide/local | E29: No verified project | F29: n/a | G29: n/a | H29: n/a | I29: n/a | J29: No verified project | K29: n/a | L29: n/a | N29: =IF(M29="","",M29-'Read Me'!$B$30) | O29: n/a | P29: n/a | Q29: n/a | R29: n/a | S29: n/a | T29: n/a | U29: n/a | V29: Not researched: search budget exhausted. CT has no statewide citizen initiative, so look at town referendum petitions on budgets and ordinances and at 2027 municipal candidate petitions. Needs a follow-up pass. | AA29: Pass 1 + Pass 2 | AB29: 46319
A30: P029 | B30: Delaware | C30: Northeast | D30: Statewide/local | E30: No verified project | F30: n/a | G30: n/a | H30: n/a | I30: n/a | J30: No verified project | K30: n/a | L30: n/a | N30: =IF(M30="","",M30-'Read Me'!$B$30) | O30: n/a | P30: n/a | Q30: n/a | R30: n/a | S30: n/a | T30: n/a | U30: n/a | V30: Not researched: search budget exhausted. Delaware has no statewide citizen initiative. Needs a follow-up pass on municipal petitions and minor-party ballot access. | AA30: Pass 1 + Pass 2 | AB30: 46319
A31: P030 | B31: District of Columbia | C31: Northeast | D31: Citywide | E31: Initiative 87: DC Living Wage for All ($25 minimum wage) | F31: Raise DC minimum wage to $25 by July 1, 2029 and phase out tipped subminimum by 2031 | G31: Initiative (DC citywide) | H31: One Fair Wage (president Saru Jayaraman); proposer Trupti Patel per 51st | I31: unknown | J31: Active – paid unconfirmed | K31: About 26,000 per Hoodline (5% of registered voters citywide and in 5 of 8 wards) | L31: 180 days from petition adoption (exact date unknown); target is a 2027 DC special election | N31: =IF(M31="","",M31-'Read Me'!$B$30) | O31: unknown (organizers declined to say for the first attempt) | P31: unknown | Q31: Volunteer shift signup via Mobilize on https://onefairwage.org/dc (no paid positions listed) | R31: unknown | S31: Saru Jayaraman, President, One Fair Wage | T31: One Fair Wage, 275 7th Ave, 15th Floor, New York, NY 10001 | U31: https://onefairwage.org/dc | V31: Missed the Nov 2026 ballot. The OFW site says collection is underway for a 2027 special election; Jayaraman said collection would start July 2026. No evidence of paid circulators (sign-up is volunteer shifts). DC non-resident circulators must register with BOE before circulating. | W31: https://onefairwage.org/dc | X31: https://hoodline.com/2026/07/d-c-wage-war-put-on-ice-after-25-ballot-bid-misses-mark/ | Y31: https://washingtonian.com/2026/07/17/advocates-of-25-minimum-wage-in-dc-blame-lawsuit-for-ballot-delay/ | Z31: https://51st.news/dc-ballot-initiatives-2026-election/ | AA31: Pass 2 (gap-fill) | AB31: 46319
A32: P031 | B32: District of Columbia | C32: Northeast | D32: Citywide | E32: Other proposed DC initiatives at BOE hearing stage (DC Equal Homeownership Act; Vermelle Paid Maternity Leave Act; DC Cash Payment Reparations Act; Human Environment 'Block Up Plan') | F32: Various; only hearing notices and advisory opinions are posted | G32: Initiative (DC citywide), pre-circulation | H32: unknown | I32: unknown | J32: Upcoming | K32: 5% of registered voters citywide and in 5 of 8 wards (about 24,000) | L32: 180 days after petition adoption (not yet adopted / unknown) | N32: =IF(M32="","",M32-'Read Me'!$B$30) | O32: unknown | P32: unknown | Q32: unknown | R32: unknown | S32: unknown | T32: DC BOE Voter Services (202) 727-2525, voterservices@dcboe.org | U32: https://dcboe.org/ballot-measures/current-measures | V32: These are listed on the BOE Current Measures page with no proposer or circulation dates shown. Approval for circulation is not confirmed. DC Referendum 009 (tipped wage timeline, Oct 2025) and Initiative 84 (Time Stability) also appear there; their current status was not verified. | W32: https://dcboe.org/ballot-measures/current-measures | X32: https://www.dcboe.org/getmedia/b8938d4f-b7c7-4912-8e9a-6287b1783db1/FINAL-Circulating-and-Filing-Initiative-Ref-Measure-Petitions-12152025.pdf | AA32: Pass 2 (gap-fill) | AB32: 46319
A33: P032 | B33: District of Columbia | C33: Northeast | D33: Citywide | E33: Initiative 88: Rent Control and Housing Eligibility Adjustment Amendment Act of 2026 (rent freeze) | F33: Two-year rent freeze on multifamily housing, plus extra 12-month freezes when DC-area CPI exceeds 5% | G33: Initiative (DC citywide) | H33: More Affordable D.C. (committee) | I33: unknown | J33: Upcoming | K33: About 24,000 valid (5% of registered voters citywide, incl. 5% in 5 of 8 wards) | L33: 180 days from final approval once litigation clears; earliest ballot is the expected spring 2027 special election | N33: =IF(M33="","",M33-'Read Me'!$B$30) | O33: unknown | P33: unknown | Q33: unknown | R33: unknown | S33: unknown | T33: unknown | U33: https://secure.actblue.com/donate/dcaffordability (committee donation page) | V33: Litigation blocked collection. A challenge led by the DC Building Industry Association coalition was denied as untimely on Sept 16, 2026; an appeal was filed Sept 18. Whether circulation has started is unknown. Opposition (DCBIA, NAR) is well funded, so a well-funded drive is plausible, but that is not confirmed. | W33: https://www.ballardspahr.com/insights/alerts-and-articles/2026/07/july-2026-dc-multifamily-update | X33: https://www.ballardspahr.com/insights/alerts-and-articles/2026/09/sept-23-2026-multifamily-client-alert | Y33: https://www.credaily.com/?p=222981 | Z33: https://www.nar.realtor/news/real-estate-news/nar-joins-challenge-to-d-c-rent-freeze-ballot-initiative; https://dcboe.org/ballot-measures/current-measures | AA33: Pass 2 (gap-fill) | AB33: 46319
A34: P033 | B34: District of Columbia | C34: Northeast | D34: Citywide | E34: Initiative 86: Prohibiting the Force-Feeding of Birds (foie gras ban) | F34: Ban sale of foie gras produced by force-feeding | G34: Initiative (DC citywide) | H34: Pro-Animal DC (campaign committee) | I34: unknown | J34: Completed/Expired | K34: 23,940 valid | L34: Qualified Aug 5, 2026; on Nov 3, 2026 ballot | M34: 46239 | N34: =IF(M34="","",M34-'Read Me'!$B$30) -> -80 | O34: 46,020 submitted; 31,726 valid; 198 circulators over 14 weeks | P34: unknown | Q34: unknown | R34: unknown | S34: unknown | T34: unknown | U34: unknown | V34: Collection is complete. Included as a reference point for what a DC drive takes (198 circulators, 14 weeks, record-setting signature count). | W34: https://www.popville.com/2026/08/force-fed-foie-gras-prohibition-dc-i86-qualifies-for-nov-ballot/ | AA34: Pass 2 (gap-fill) | AB34: 46319
A35: P034 | B35: Florida | C35: Southeast | D35: Statewide | E35: Florida Decides Healthcare - Medicaid expansion (2028) | F35: Constitutional amendment to expand Medicaid to adults 18-64 with incomes at or below 138% of the federal poverty level | G35: Statewide citizen initiative constitutional amendment | H35: Florida Decides Healthcare (Executive Director Mitch Emerson) | I35: unknown for 2028. For the 2026 drive, The Outreach Team posted paid 'Petitioner' jobs (posted April 8, 2025). | J35: Active – paid unconfirmed | K35: 880,062 was the 2026-cycle requirement (8% of voters). The exact 2028 figure is unknown. | L35: Feb 1, 2028 (standard Florida deadline for the 2028 ballot; not separately confirmed in sources) | M35: 46784 | N35: =IF(M35="","",M35-'Read Me'!$B$30) -> 465 | O35: Brevard County: 100 valid in total (7 valid 9/1-9/30/2026) as of 9/30/2026. Monroe County: 125 verified as of 1/30/2026. Statewide 2028 total unknown. The 2026 drive validated 75,855 of 90,250 submitted. | P35: 2026 drive (The Outreach Team, April 2025 posting): $19/hr for circulators, $21-25/hr for leadership, +$1/hr bilingual. The 2028 rate is unknown. | Q35: https://careers.arena.run/companies/the-outreach-team-2/jobs/48573140-petitioner-help-expand-medicaid-in-florida (2025 posting for the 2026 drive; current status unknown) | R35: unknown | S35: Mitch Emerson, Executive Director (per AP/CBS) | T35: unknown | U35: https://floridadecideshealthcare.org | V35: Relaunched signature collection for 2028 on Feb 1, 2026. The new model is mail-in petitions (prepaid return envelope) requested through the website, plus 100+ grassroots partners; that model points away from paid field circulation. Brevard's monthly valid count is small (7 in September 2026), which points to low field activity. The group says HB 1205 'dramatically increased petition costs.' It was lead plaintiff in Florida Decides Healthcare v. Byrd. On April 30, 2026, Judge Walker upheld the circulator registration requirement, the out-of-state and non-citizen circulator bans, felon restrictions, the $50,000-per-violation fine and the felony for filling in petition information. Ballot Access News reported the plaintiffs did not plan to appeal (BAN's May 1 post said the ruling would be appealed, so these conflict). The Florida DOS initiative database (constitutionalinitiatives.dos.fl.gov) was blocked by Cloudflare and could not be checked directly. | W35: https://www.beckerspayer.com/payer/medicaid/florida-medicaid-expansion-campaign-sets-sights-on-2028-ballot/ | X35: https://floridaphoenix.com/2026/04/30/federal-judge-upholds-floridas-citizen-initiative-restrictions/ | Y35: https://careers.arena.run/companies/the-outreach-team-2/jobs/48573140-petitioner-help-expand-medicaid-in-florida | Z35: https://jobs.arena.run/jobs/field-director-recx-ua8s9k-n6-fw-cq-p; https://www.cbsnews.com/amp/miami/news/campaign-delays-push-to-expand-medicaid-in-florida-until-2028-citing-new-state-law; https://jaxtoday.org/2026/02/02/constitutional-amendments-florida-failed/; https://www.votebrevard.gov/Voter-Data-and-Maps/Statistics-and-Data/Initiative-Petition-Totals; https://www.votemonroeflkeys.gov/Candidates-Petitions/Initiative-Petitions | AA35: Pass 1 + Pass 2 | AB35: 46319
A36: P035 | B36: Florida | C36: Southeast | D36: Statewide | E36: Defending Unborn Life (Initiative 25-06) | F36: Anti-abortion constitutional amendment (title only; full text not reviewed) | G36: Statewide citizen initiative constitutional amendment | H36: unknown (state volunteer petition form DSDE155A_999_2506 exists) | I36: unknown | J36: Active – paid unconfirmed | K36: unknown for 2028 | L36: Feb 1, 2028 (standard Florida deadline; not separately confirmed) | M36: 46784 | N36: =IF(M36="","",M36-'Read Me'!$B$30) -> 465 | O36: Brevard County: 5 valid as of 9/30/2026. Statewide total unknown. | P36: unknown | Q36: unknown | R36: unknown | S36: unknown | T36: unknown | U36: unknown | V36: Listed as an active initiative on the Brevard SOE totals page (9/30/2026). The volunteer form suggests volunteer collection. The very low count points to no meaningful paid drive. | W36: https://www.votebrevard.gov/Voter-Data-and-Maps/Statistics-and-Data/Initiative-Petition-Totals | X36: https://initiativepetitions.dos.fl.gov/InitiativeForms/Volunteer/DSDE155A_999_2506_EN.pdf | AA36: Pass 1 | AB36: 46319
A37: P036 | B37: Florida | C37: Southeast | D37: City of Fort Meade (Polk County) | E37: Fort Meade recall - Mayor Jaret Williams, Vice Mayor Petrina McCutchen, Commissioner Mathew Taylor | F37: Recall three city officials after approval of a 4.4-million-sq-ft Stonebridge hyperscale data center | G37: Municipal recall petition | H37: Fort Meade recall committee (chair Michael Bennett; Watchdogs of Fort Meade involved) | I37: unknown (appears volunteer) | J37: Active – paid unconfirmed | K37: First phase ~10% (about 246 minimum per organizer); second phase 15% of registered voters (~400) | L37: unknown | N37: =IF(M37="","",M37-'Read Me'!$B$30) | O37: More than 1,000 first-phase signatures submitted to City Hall (July 17, 2026) | P37: unknown | Q37: unknown | R37: unknown | S37: Michael Bennett (committee chair) | T37: unknown | U37: unknown | V37: Appears resident-led; no evidence of paid circulators. Status after the July 2026 SOE verification is unknown. Listed as a local petition opportunity, not a confirmed paid job. | W37: https://baynews9.com/fl/tampa/news/2026/07/17/fort-meade-recall-committee-submits-petitions-to-remove-city-leaders | X37: https://mynews13.com/fl/orlando/news/2026/07/17/fort-meade-recall-committee-submits-petitions-to-remove-city-leaders | Y37: https://www.tampabay28.com/news/region-polk/recall-effort-targets-three-fort-meade-city-leaders-after-data-center-approval | AA37: Pass 1 + Pass 2 | AB37: 46319
A38: P037 | B38: Florida | C38: Southeast | D38: City of Miami (Miami-Dade County) | E38: Stronger Miami charter amendment petition | F38: Change the City of Miami charter: expand the commission from 5 to 9 districts, move city elections to even years starting 2028, and set neighborhood-preserving, non-partisan redistricting rules | G38: Municipal charter amendment citizen petition | H38: Stronger Miami Coalition (One Grove Alliance, Florida Rising and other nonprofits) | I38: unknown | J38: Active – paid unconfirmed | K38: About 20,000 certified signatures | L38: unknown | N38: =IF(M38="","",M38-'Read Me'!$B$30) | O38: About 20,500 submitted; as of Feb 25, 2026, 13,416 reviewed, 7,203 certified, 6,213 uncertified, ~5,000 under review plus ~1,000 more turned in | P38: unknown | Q38: unknown | R38: unknown | S38: Teresa Guzman Pagan, Florida Rising (quoted director) | T38: unknown | U38: https://floridarising.org (coalition member) | V38: Latest verified status is Feb 2026. Whether it later qualified or is still collecting is unknown; the search budget ran out before this could be checked. The ~30% invalid rate suggests heavy field collection, but paid circulation is not confirmed. | W38: https://www.wlrn.org/government-politics/2026-02-26/stronger-miami-petition-ballot-miami | X38: https://www.wlrn.org/government-politics/2026-02-23/stronger-miami-government-petition-ballot-signatures | AA38: Pass 1 | AB38: 46319
A39: P038 | B39: Florida | C39: Southeast | D39: Statewide | E39: Floridians for Marijuana (2028 adult-use cannabis initiative) | F39: Constitutional amendment legalizing adult-use cannabis | G39: Statewide citizen initiative constitutional amendment | H39: Floridians for Marijuana political committee (chair Zack Whitson, treasurer Gloria Maggiolo) | I39: unknown | J39: Upcoming | K39: unknown for 2028 (8% of votes in the last presidential election; ~880,000 range per reporting) | L39: Feb 1, 2028 (standard Florida deadline; not separately confirmed) | M39: 46784 | N39: =IF(M39="","",M39-'Read Me'!$B$30) -> 465 | O39: unknown | P39: unknown | Q39: unknown | R39: unknown | S39: Zack Whitson (chair) | T39: unknown | U39: unknown | V39: Petition approved by the Division of Elections on Sept 30, 2026. No signature count, funding or circulation firm was found. A registered petition is not the same as active paid circulation. | W39: https://www.cannabisbusinesstimes.com/us-states/florida/news/15836634/florida-may-have-3-options-to-legalize-adultuse-cannabis-in-2028 | AA39: Pass 1 + Pass 2 | AB39: 46319
A40: P039 | B40: Florida | C40: Southeast | D40: Statewide | E40: Let Florida Vote IV (2028 cannabis initiative) | F40: Constitutional amendment legalizing adult-use cannabis | G40: Statewide citizen initiative constitutional amendment | H40: Political committee chaired by Zack Whitson (treasurer Gloria Maggiolo) | I40: unknown | J40: Upcoming | K40: unknown for 2028 | L40: Feb 1, 2028 (standard Florida deadline; not separately confirmed) | M40: 46784 | N40: =IF(M40="","",M40-'Read Me'!$B$30) -> 465 | O40: unknown | P40: unknown | Q40: unknown | R40: unknown | S40: Zack Whitson (chair) | T40: unknown | U40: unknown | V40: Pending with the Financial Impact Estimating Conference as of Sept 29, 2026, per Cannabis Business Times. The wording suggests it has already crossed the 25% review threshold, but that is not stated, so treat the count as unknown. | W40: https://www.cannabisbusinesstimes.com/us-states/florida/news/15836634/florida-may-have-3-options-to-legalize-adultuse-cannabis-in-2028 | AA40: Pass 1 + Pass 2 | AB40: 46319
A41: P040 | B41: Florida | C41: Southeast | D41: Statewide | E41: Smart & Safe Florida - Adult Personal Use of Marijuana (2028 effort) | F41: Constitutional amendment legalizing adult personal use of marijuana for the 2026 ballot | G41: Statewide citizen initiative constitutional amendment | H41: Smart & Safe Florida (backed by Trulieve) | I41: unknown (the committee cited 474 trained circulators, including out-of-state circulators until May 2, 2025) | J41: Completed/Expired | K41: 880,062 | L41: Feb 1, 2026 (passed) | M41: 46054 | N41: =IF(M41="","",M41-'Read Me'!$B$30) -> -265 | O41: About 1.4 million claimed submitted; 783,592 validated (as of Feb 2, 2026). Failed to qualify. | P41: unknown | Q41: unknown | R41: Trulieve contributed $67 million | S41: unknown | T41: unknown | U41: unknown | V41: Paid circulation is confirmed by a headline about a 'paid petitioner working for Florida cannabis campaign' (Ganjapreneur; article body not fetched). HB 1205 impact per the committee's court filing: out-of-state circulators were dropped on May 2, 2025; about 600 Florida-resident circulators stopped because of the 10-day return rule; weekly collection fell about one-third from ~78,000/week; and lawyers estimated $23.7M in potential fines ($50k x 474 circulators). Nearly 71,000 signatures were disqualified, and the AG opened fraud probes. All 22 active initiatives failed to make the 2026 ballot. | W41: https://www.cannabisbusinesstimes.com/us-states/florida/news/15836634/florida-may-have-3-options-to-legalize-adultuse-cannabis-in-2028 | X41: https://www.orlandoweekly.com/cannabis/trulieve-pours-nearly-20m-into-floridas-latest-recreational-marijuana-effort-39293879/ | Y41: https://thecapitolist.com/statewide-prosecutors-ask-fdle-to-investigate-petition-circulators-tied-to-marijuana-initiative/ | Z41: https://www.clickorlando.com/news/florida/2026/02/02/no-citizen-initiatives-on-2026-florida-ballot-including-marijuana-amendment-state-says/; https://jaxtoday.org/2026/02/02/constitutional-amendments-florida-failed/; https://www.orlandoweekly.com/cannabis/backers-of-floridas-new-recreational-marijuana-initiative-argue-its-unlikely-to-reach-voters-without-help-from-the-courts-39659978; https://ganjapreneur.com/paid-petitioner-working-for-florida-cannabis-campaign-accused-of-submitting-fraudulent-signatures/ | AA41: Pass 1 + Pass 2 | AB41: 46319
A42: P041 | B42: Florida | C42: Southeast | D42: Statewide | E42: Right to Clean and Healthy Waters (Initiative 24-03) | F42: Constitutional amendment on a right to clean water | G42: Statewide citizen initiative constitutional amendment | H42: unknown | I42: unknown | J42: Completed/Expired | K42: 880,062 (2026 cycle) | L42: Feb 1, 2026 (passed) | M42: 46054 | N42: =IF(M42="","",M42-'Read Me'!$B$30) -> -265 | O42: Monroe County: 633 verified as of 1/30/2026. Statewide unknown. | P42: unknown | Q42: unknown | R42: unknown | S42: unknown | T42: unknown | U42: unknown | V42: All 22 active initiatives failed for 2026. It was not listed on the Brevard 9/30/2026 active totals page, so a 2028 continuation is not confirmed. | W42: https://www.votemonroeflkeys.gov/Candidates-Petitions/Initiative-Petitions | X42: https://jaxtoday.org/2026/02/02/constitutional-amendments-florida-failed/ | AA42: Pass 1 | AB42: 46319
A43: P042 | B43: Florida | C43: Southeast | D43: Statewide / U.S. House districts | E43: Minor-party / NPA candidate and party ballot-access petitions – 2026 | F43: Candidate ballot access by petition after the HB 1D redistricting | G43: Candidate/party ballot access | H43: Various minor-party candidates | I43: unknown | J43: Completed/Expired | K43: 2,564 per U.S. House district (collectable statewide) | L43: May 11, 2026 (U.S. House); April 24 for statewide party petitions (passed) | M43: 46153 | N43: =IF(M43="","",M43-'Read Me'!$B$30) -> -166 | O43: Seven minor-party U.S. House candidates filed | P43: unknown | Q43: unknown | R43: unknown | S43: unknown | T43: unknown | U43: unknown | V43: Per Ballot Access News, June 2026. Libertarian, Green, Constitution and Forward are already qualified in Florida. The Florida Reform Party was removed for failing to file finance reports. No paid circulation was evidenced. | W43: https://ballot-access.org/2026/06/22/june-2026-ballot-access-news-print-edition/ | AA43: Pass 1 | AB43: 46319
A44: P043 | B44: Florida | C44: South | D44: Sebastian (Indian River County) | E44: Sebastian City Council recall (Gilliams, Parris, Mauti) | F44: Recall council members | G44: Municipal recall | H44: PAC led by Tracey Cole | I44: unknown | J44: Completed/Expired | K44: unknown | L44: unknown | N44: =IF(M44="","",M44-'Read Me'!$B$30) | O44: over 7,400 (per sebastiandaily headline) | P44: unknown | Q44: unknown | R44: unknown | S44: unknown | T44: unknown | U44: unknown | V44: Search results showed 2026 dates, but these are the site's header date; the article was published Aug 3, 2020. This is a 2020 recall, not current. Included to prevent mis-use. | W44: https://www.sebastiandaily.com/community/supervisor-of-elections-receives-petitions-to-recall-damien-gilliams-pamela-parris-charles-mauti-24478/ | AA44: Pass 2 (gap-fill) | AB44: 46319
A45: P044 | B45: Georgia | C45: South | D45: Hall County | E45: Recall of Hall County Sheriff Gerald Couch | F45: Recall sheriff | G45: County recall (Georgia Recall Act) | H45: Concerned Citizens of Hall County | I45: unknown | J45: Completed/Expired | K45: 42,080 (30% of registered voters) | L45: September 3 2026 | M45: 46268 | N45: =IF(M45="","",M45-'Read Me'!$B$30) -> -51 | O45: roughly 2,000-3,000 as of Aug 5 2026 | P45: unknown | Q45: unknown | R45: unknown | S45: unknown | T45: unknown | U45: unknown | V45: Deadline passed; final outcome not verified. Far behind pace as of Aug 5. | W45: https://www.wsbtv.com/news/held-higher-standard-group-gathering-signatures-remove-hall-county-sheriff-office/BEOM4VVZIJC5PJTIKPVZ5HHIMU/ | AA45: Pass 2 (gap-fill) | AB45: 46319
A46: P045 | B46: Hawaii | C46: West | D46: Statewide / counties | E46: County charter petitions or recalls - none verified | F46: N/A | G46: N/A (Hawaii has no statewide citizen initiative process; county charter initiative/recall petitions exist) | H46: unknown | I46: unknown | J46: No verified project | K46: unknown | L46: unknown | N46: =IF(M46="","",M46-'Read Me'!$B$30) | O46: unknown | P46: unknown | Q46: unknown | R46: unknown | S46: unknown | T46: unknown | U46: unknown | V46: Hawaii has no statewide initiative or referendum, so only county-level petitions are possible. A planned search of county charter/recall petitions (Honolulu, Maui, Hawaii County, Kauai) was not run because the search budget ran out. Nothing verified. | W46: https://www.civilbeat.org/2026/10/list-hawaiis-2026-charter-and-constitutional-amendments/ | X46: https://news.ballotpedia.org/?p=51538 | AA46: Pass 1 + Pass 2 | AB46: 46319
A47: P046 | B47: Idaho | C47: Mountain/Southwest | D47: Statewide | E47: Reproductive Freedom and Privacy Act (end Idaho's abortion ban) | F47: Restore abortion access via statute | G47: Statewide initiated statute | H47: Idahoans United for Women and Families (Exec. Dir. Melanie Folwell) | I47: unknown | J47: Completed/Expired | K47: 70,725 valid statewide (6%) plus 6% in 18 of 35 legislative districts | L47: April 30, 2026 (submitted; reported qualified) | M47: 46142 | N47: =IF(M47="","",M47-'Read Me'!$B$30) -> -177 | O47: About 104,000-110,000 submitted | P47: unknown | Q47: unknown | R47: unknown | S47: Melanie Folwell | T47: unknown | U47: unknown | V47: Whether circulators were paid is not stated in the sources. The drive is completed. | W47: https://idahocapitalsun.com/2026/04/24/group-seeking-to-end-idahos-abortion-ban-says-its-met-signature-goal-in-19-legislative-districts/ | X47: https://www.eastidahonews.com/?p=849093 | Y47: https://newsletters.idahocapitalsun.com/p/initiative-ending-abortion-ban-qualifies-albertsons-trial-begins-cole-reappointed-to-cdh-board | AA47: Pass 1 | AB47: 46319
A48: P047 | B48: Idaho | C48: Mountain/Southwest | D48: Statewide | E48: Idaho medical cannabis initiative | F48: Legalize medical cannabis | G48: Statewide initiated statute | H48: Natural Medicine Alliance of Idaho | I48: Two unnamed paid vendors (the original vendor's work is under scrutiny; a second firm was brought in late) | J48: Completed/Expired | K48: 70,725 valid plus 6% in 18 of 35 districts | L48: April 30, 2026; failed to qualify (July 14, 2026) | M48: 46142 | N48: =IF(M48="","",M48-'Read Me'!$B$30) -> -177 | O48: Max 58,024 certified; threshold met in only 13 districts | P48: unknown | Q48: unknown | R48: unknown | S48: unknown | T48: unknown | U48: unknown | V48: Paid circulation is confirmed, but the drive failed. The sponsor is weighing legal remedies. A vendor-quality failure like this is a pitch angle for a 2028 retry. Vendor names are unknown. | W48: https://idahocapitalsun.com/2026/07/14/medical-cannabis-initiative-fails-to-qualify-for-idahos-general-election-ballot/ | X48: https://www.boisestatepublicradio.org/politics-government/2026-07-15/pot-cannabis-weed-election-november-idaho-citizen-initiative | AA48: Pass 1 | AB48: 46319
A49: P048 | B49: Illinois | C49: Great Lakes | D49: City of Chicago | E49: Chicago Feb 23, 2027 municipal election – nominating petitions (mayor, clerk, treasurer, 50 aldermen, police district councils) | F49: Candidate ballot access | G49: Candidate nominating petitions | H49: Individual campaigns (filed so far: Alexi Giannoulias, John Kelly, Willie Wilson, Matt Brewer, Mike Quigley; others expected incl. Brandon Johnson, Susana Mendoza, Maria Pappas) | I49: unknown | J49: Active – paid unconfirmed | K49: 12,500 valid for mayor/clerk/treasurer; 473 per ward for alderman | L49: Filing Oct 19–26, 2026 (5 p.m. Oct 26); objections due Nov 2; ballot certified Dec 17, 2026 | M49: 46314 | N49: =IF(M49="","",M49-'Read Me'!$B$30) -> -5 | O49: Self-reported: Giannoulias ~60,000; Kelly 36,000+; Wilson ~35,000; Brewer 32,000+ | P49: unknown | Q49: unknown | R49: unknown | S49: Individual campaign managers (unknown) | T49: Chicago Board of Election Commissioners (filing office); campaign contacts unknown | U49: https://app.chicagoelections.gov | V49: Collection began July 28, 2026; filing closes Oct 26, two days from now. Collection is basically over, but the petition challenge/objection phase (Nov 2 onward) creates demand for petition review and validation work. No paid circulator evidence found. | W49: https://chicago.suntimes.com/elections/2026/10/19/mayor-race-candidates-stacks-nominating-petitions-chicago-board-of-elections | X49: https://www.axios.com/local/chicago/2026/10/19/chicago-mayoral-hopefuls-file-petitions-amid-controversy | Y49: https://news.wttw.com/node/54511 | AA49: Pass 1 | AB49: 46319
A50: P049 | B50: Illinois | C50: Great Lakes | D50: Statewide (local units outside Chicago, e.g. St. Clair County calendar) | E50: April 6, 2027 Consolidated Election – nonpartisan/independent nominating petitions and local referenda petitions | F50: Ballot access for school, library, park, fire, community college and other nonpartisan offices; local public-policy referenda | G50: Candidate nominating petitions; local referendum petitions | H50: Various candidates and local petitioners | I50: unknown | J50: Active – paid unconfirmed | K50: Varies by office and unit (unknown) | L50: Nominating papers filed Nov 16–23, 2026; petitions to create a political subdivision due Dec 7, 2026; local public-policy referenda petitions due Jan 4, 2027; party caucus certificates Dec 14–21, 2026 | M50: 46342 | N50: =IF(M50="","",M50-'Read Me'!$B$30) -> 23 | O50: unknown | P50: unknown | Q50: unknown | R50: unknown | S50: unknown | T50: Local election authorities / county clerks (e.g. St. Clair County Clerk) | U50: https://www.stclaircountyil.gov | V50: Circulation opened Aug 25, 2026. This is the live Illinois petition window, with referendum petitions due Jan 4, 2027. I found no specific paid local referendum drive. This is a calendar opportunity, not a confirmed paid project. | W50: https://www.stclaircountyil.gov/webdocuments/departments/countyclerk/2027Resources/2027 Election Calendar FINAL (1).pdf | AA50: Pass 1 | AB50: 46319
A51: P050 | B51: Illinois | C51: Great Lakes | D51: Chicago | E51: TouchStone LLC – signature gathering canvassers (Oct 2025 posting) | F51: Signature collection to qualify a major initiative for the ballot, and to support a progressive candidate's ballot access (per posting) | G51: Paid petition circulation job (initiative and candidate) | H51: unknown (vendor posting) | I51: TouchStone, LLC | J51: Completed/Expired | K51: unknown | L51: Job ran Oct 15–26, 2025 | M51: 45945 | N51: =IF(M51="","",M51-'Read Me'!$B$30) -> -374 | O51: unknown | P51: $25–$30/hour, paid weekly | Q51: https://careers.arena.run/companies/job-post-2/jobs/60314310-touchstone-llc-signature-gathering-canvassers-needed-25-30-hour-chicago-il | R51: unknown | S51: unknown | T51: unknown (email partly obscured on the posting) | U51: unknown | V51: Posted Oct 11, 2025. Confirmed paid but expired. Useful as an Illinois hourly pay benchmark and as an Illinois vendor name. | W51: https://careers.arena.run/companies/job-post-2/jobs/60314310-touchstone-llc-signature-gathering-canvassers-needed-25-30-hour-chicago-il | AA51: Pass 1 | AB51: 46319
A52: P051 | B52: Indiana | C52: Great Lakes | D52: Statewide | E52: Greg Ballard independent Secretary of State petition / Lincoln Party ballot access | F52: Ballot access for an independent statewide candidate; a 2% vote share would give the Lincoln Party 4-year ballot access | G52: Independent candidate ballot access petition | H52: Ballard campaign; Lincoln Party (chair Nathan Gotsch); Independent Indiana nonprofit | I52: unknown | J52: Completed/Expired | K52: ~37,000 (2% of the last SOS vote) | L52: Delivered July 14, 2026 (official deadline unknown) | M52: 46217 | N52: =IF(M52="","",M52-'Read Me'!$B$30) -> -102 | O52: 52,000+ (campaign claim); Ballard is on the Nov 2026 ballot | P52: unknown | Q52: unknown | R52: unknown | S52: Greg Ballard; Nathan Gotsch (Lincoln Party chair) | T52: unknown | U52: unknown | V52: Coverage mentions volunteers and signature gatherers, with no paid vendor named. State Police investigated one volunteer's fraudulent page. If the Lincoln Party wins 2%+ on Nov 3, future candidates skip petitions; if not, it is a possible petition client for 2028. | W52: https://indianacapitalchronicle.com/briefs/independent-secretary-of-state-hopeful-says-he-has-the-signatures/ | X52: https://www.newsfromthestates.com/node/426505 | AA52: Pass 1 | AB52: 46319
A53: P052 | B53: Iowa | C53: Plains/Texas | D53: Statewide / local | E53: Local referendum/recall/charter petitions | F53: n/a | G53: n/a | H53: n/a | I53: n/a | J53: No verified project | K53: n/a | L53: n/a | N53: =IF(M53="","",M53-'Read Me'!$B$30) | O53: n/a | P53: unknown | Q53: unknown | R53: unknown | S53: n/a | T53: n/a | U53: n/a | V53: Iowa has no statewide citizen initiative. Local, recall and ballot-access petitions were NOT searched because the shared web-search budget ran out before Iowa was reached. This is a research gap, not a confirmed absence. | W53: https://www.minneapolismn.gov/government/boards-and-commissions/charter-commission/amending-the-charter/ | X53: https://www.kwit.org/podcast/spm-news/2026-02-16/spencer-iowa-residents-force-special-election-for-city-council-post | AA53: Pass 1 + Pass 2 | AB53: 46319
A54: P053 | B54: Kansas | C54: Central | D54: Ottawa (Franklin County) | E54: Ottawa data center ban initiative ordinance | F54: Ban data centers using more than 25 MW within Ottawa city limits | G54: Municipal initiative ordinance | H54: Citizen petition led by Jessica Christopher ('We the People Ottawa' per KSHB headline) | I54: unknown (appears volunteer) | J54: Completed/Expired | K54: 658 | L54: Verified Aug 7, 2026. Commission had 20 days to adopt, otherwise it goes to the voters. Lightfield entitlement period ends Oct 30, 2026 | M54: 46241 | N54: =IF(M54="","",M54-'Read Me'!$B$30) -> -78 | O54: 1,031 signed (claimed) | P54: unknown | Q54: unknown | R54: unknown | S54: Jessica Christopher | T54: unknown | U54: unknown | V54: Signature phase complete. A similar Emporia, KS petition (about 1,400 signatures against the Digital Campus, July 2026) was also found, but its article could not be fetched. | W54: https://www.kshb.com/news/local-news/data-centers/ottawa-commissioners-face-deadline-after-data-center-petition-gains-enough-signatures | X54: https://www.kshb.com/news/local-news/data-centers/we-the-people-ottawa-ballot-petition-seeks-ordinance-to-ban-future-data-center-developments | AA54: Pass 2 (gap-fill) | AB54: 46319
A55: P054 | B55: Kentucky | C55: Southeast | D55: Statewide | E55: Local recall/referendum/charter petitions | F55: Ballot access (Kentucky has no statewide citizen initiative) | G55: Candidate/party ballot access | H55: unknown | I55: unknown | J55: No verified project | K55: Independent 5,000; party: no procedure | L55: Aug 11, 2026 (passed) | M55: 46245 | N55: =IF(M55="","",M55-'Read Me'!$B$30) -> -74 | O55: unknown | P55: unknown | Q55: unknown | R55: unknown | S55: unknown | T55: unknown | U55: unknown | V55: Checked Ballot Access News June 2026 only. Kentucky has a 2027 statewide election (governor), so independent petitions for 2027 are plausible, but none was verified. Job boards were not searched because the search budget ran out. | W55: https://ballot-access.org/2026/06/22/june-2026-ballot-access-news-print-edition/ | AA55: Pass 1 + Pass 2 | AB55: 46319
A56: P055 | B56: Louisiana | C56: South | D56: Statewide | E56: Recall of Gov. Jeff Landry (and AG Liz Murrill) | F56: Recall governor (attorney general recall also referenced in KNOE coverage) | G56: Statewide recall | H56: Recall committee; Certified Recall Petitioner Veda Emerson (others unnamed); filed by Baton Rouge residents | I56: unknown | J56: Active – paid unconfirmed | K56: 500,884 | L56: October 31 2026 (180 days from May 4 2026) | M56: 46326 | N56: =IF(M56="","",M56-'Read Me'!$B$30) -> 7 | O56: unknown | P56: unknown | Q56: unknown | R56: unknown | S56: Veda Emerson (certified recall petitioner) | T56: unknown | U56: unknown | V56: Petition began May 4 2026; deadline 7 days away. Appears volunteer-driven (fixed signing sites); no paid circulator evidence. Signature count not reported. | W56: https://www.ksla.com/2026/05/11/supporters-gather-government-plaza-recall-petition-targets-gov-jeff-landry/ | X56: https://www.knoe.com/2026/06/10/gov-jeff-landry-attorney-general-liz-murrill-recall-comes-nela/ | AA56: Pass 2 (gap-fill) | AB56: 46319
A57: P056 | B57: Maine | C57: Northeast | D57: Statewide | E57: An Act to Amend the Cannabis Legalization Act and the Maine Medical Use of Cannabis Act | F57: Roll back or restrict Maine's adult-use and medical cannabis laws (described as an anti-cannabis/prohibitionist effort) | G57: Direct initiative (indirect via Legislature) | H57: unknown (Secretary of State's 'Proponent Information' page not fetched) | I57: unknown. Out-of-state paid circulators were reported | J57: Strong evidence active paid | K57: 67,682 valid | L57: June 8, 2027 filing deadline (for a 2027 election); Feb 2, 2026 was the 2026 cutoff | M57: 46546 | N57: =IF(M57="","",M57-'Read Me'!$B$30) -> 227 | O57: unknown | P57: $1 per signature (one circulator, in a recording reported Jan 2026) | Q57: unknown | R57: unknown | S57: unknown | T57: Maine Division of Elections 207-624-7650 (state office, for proponent records) | U57: https://www.maine.gov/sos/elections-voting/peoples-veto-or-citizens-initiative-resources/current-citizen-initiatives-and-peoples-vetoes | V57: Approved for circulation Dec 8, 2025. In Jan 2026, Secretary Bellows testified that circulators were 'people for hire' shipped in from out of state. A Texas circulator said he was paid $1 per signature. The SOS page still lists it as current, with a June 8, 2027 deadline. Not verified whether signatures were filed for 2026 or whether paid collection continues in Oct 2026. | W57: https://www.maine.gov/sos/elections-voting/peoples-veto-or-citizens-initiative-resources/current-citizen-initiatives-and-peoples-vetoes | X57: https://www.cannabisbusinesstimes.com/us-states/maine/news/15814590/maine-anticannabis-signature-gatherers-allowed-to-lie-about-petition | AA57: Pass 1 | AB57: 46319
A58: P057 | B58: Maine | C58: Northeast | D58: Statewide | E58: Resolve directing development of a publicly funded health care system for all Maine residents | F58: Direct the Legislature to develop universal publicly funded health care | G58: Direct initiative (resolve), targeting the 2027 ballot | H58: Maine AllCare / HealthCare for All Maine (501(c)(4) arm) | I58: unknown (appears volunteer-driven; commenters describe themselves as canvassers) | J58: Active – paid unconfirmed | K58: 67,682 valid | L58: April 24, 2027 filing deadline | M58: 46501 | N58: =IF(M58="","",M58-'Read Me'!$B$30) -> 182 | O58: unknown | P58: unknown | Q58: unknown | R58: unknown | S58: unknown | T58: Maine AllCare, PO Box 190, Manchester, ME 04351; info@maineallcare.org | U58: https://maineallcare.org/ ; https://healthcareforallmaine.org | V58: Approved for circulation Oct 24, 2025. A July 2, 2026 post describes an active campaign for the 2027 ballot. No evidence of paid circulators. Possible prospect for professional field help as the deadline approaches. | W58: https://www.maine.gov/sos/elections-voting/peoples-veto-or-citizens-initiative-resources/current-citizen-initiatives-and-peoples-vetoes | X58: https://maineallcare.org/?p=158116 | AA58: Pass 1 | AB58: 46319
A59: P058 | B59: Maine | C59: Northeast | D59: Statewide | E59: An Act to Designate School Sports Participation and Facilities by Sex ('Protect Girls Sports in Maine') | F59: Limit school sports participation, and bathroom and locker room use, to sex at birth | G59: Direct initiative | H59: unknown (SOS page references a petition organization registration mentioning 'Morning in American II'; not confirmed as the applicant) | I59: unknown. Out-of-state circulators were a prominent factor in the signature review | J59: Completed/Expired | K59: 67,682 valid | L59: Petitions submitted; filing deadline listed as May 3, 2027 | M59: 46510 | N59: =IF(M59="","",M59-'Read Me'!$B$30) -> 191 | O59: unknown (SOS first validated in March 2026, then found too few valid signatures after a legal challenge) | P59: unknown | Q59: unknown | R59: unknown | S59: unknown | T59: unknown | U59: https://www.maine.gov/sos/elections-voting/peoples-veto-or-citizens-initiative-resources/current-citizen-initiatives-and-peoples-vetoes | V59: Signatures were submitted, and the review was in the courts as of May 2026. Collection appears finished. Because the issue date was Nov 3, 2025 and the window runs to May 3, 2027, a supplemental drive is possible but not verified. | W59: https://www.maine.gov/sos/elections-voting/peoples-veto-or-citizens-initiative-resources/current-citizen-initiatives-and-peoples-vetoes | X59: https://www.pressherald.com/?p=7653907 | AA59: Pass 1 | AB59: 46319
A60: P059 | B60: Maryland | C60: Northeast | D60: Montgomery County | E60: County spending cap charter amendment (Committee to Control MoCo Spending) — 2028 retry | F60: Charter amendment requiring unanimous Council vote for budget increases above inflation | G60: County charter amendment petition | H60: Committee to Control MoCo Spending (Montgomery County GOP committee) | I60: unknown | J60: Upcoming | K60: 10,000 valid | L60: unknown (2028 election target) | N60: =IF(M60="","",M60-'Read Me'!$B$30) | O60: 2026 attempt: >14,000 submitted, 302 short of valid; failed Aug 17, 2026 | P60: unknown | Q60: unknown | R60: unknown | S60: unknown | T60: unknown | U60: unknown | V60: The committee said: 'We are planning on a new ballot petition in support of the same charter amendment for the 2028 election.' It also filed for judicial review of the 2026 count. It fell short by only 302 signatures, which makes it a strong prospect for a professional validation/QC pitch. | W60: https://www.mymcmedia.org/?p=194914 | X60: https://montgomeryperspective.com/wp-content/uploads/2026/08/Committee-Control-MoCo-Spending-v-Montgo-BOE-PETITION-for-Judicial-Review-1-DOCKETED.pdf | AA60: Pass 2 (gap-fill) | AB60: 46319
A61: P060 | B61: Maryland | C61: Northeast | D61: City of Salisbury (Wicomico County) | E61: Salisbury collective bargaining ordinance repeal referendum (AFSCME) | F61: Put the City Council's May 2026 repeal of the union/collective-bargaining ordinance to voters | G61: Municipal referendum petition | H61: AFSCME Maryland (AFSCME Maryland Petitioning Project); Shore Progress also involved | I61: The Outreach Team (job ad for the AFSCME Maryland Petitioning Project, Salisbury) | J61: Completed/Expired | K61: About 4,036 (5,818 valid was 1,782 over the requirement) | L61: Petition drive done (37 days); Council placed it on the ballot Aug 10, 2026; vote Nov 2, 2027 | M61: 46244 | N61: =IF(M61="","",M61-'Read Me'!$B$30) -> -75 | O61: 5,818 valid | P61: $23/hr circulator; $25/hr team lead; $50-$150/day bonuses | Q61: https://www.theoutreachteam.net/interest-form-tot (June 2026 posting, positions ran through June 19, possible extension) | R61: unknown | S61: AFSCME Maryland | T61: https://afscmemd.org/press-room/statement-validation-petition-signatures-wicomico-county-board | U61: https://afscmemd.org | V61: Confirmed paid (job ad posted June 4, 2026), but collection is finished. The job-ad text also mentions 'campaign finance reform', which looks inconsistent. Election campaign work possible ahead of Nov 2, 2027. | W61: https://www.wmdt.com/?p=4615385 | X61: https://www.monmouth.edu/career-development/wp-json/wp/v2/ch_job/20163 | Y61: https://afscmemd.org/press-room/statement-validation-petition-signatures-wicomico-county-board | AA61: Pass 2 (gap-fill) | AB61: 46319
A62: P061 | B62: Maryland | C62: Northeast | D62: Frederick County | E62: Frederick County data center zoning referendum | F62: Referendum on county data center overlay zoning | G62: County referendum petition | H62: Frederick County Data Center Referendum Committee (DCRC); circulators paid through Envision Frederick County using a $10,000 Chesapeake Climate Action Network grant | I62: None named (paid via Envision Frederick County) | J62: Completed/Expired | K62: About 7% of county voters | L62: Struck by Maryland Supreme Court June 30, 2026 | M62: 46203 | N62: =IF(M62="","",M62-'Read Me'!$B$30) -> -116 | O62: About 21,000-22,169 | P62: unknown | Q62: unknown | R62: $10,000 grant (CCAN) for circulators | S62: Elizabeth Bauer (DCRC board member) | T62: unknown | U62: unknown | V62: Petition ruled ineligible because the color maps were printed in black and white. WYPR says other counties have asked the DCRC for advice on their own data-center referendums, which signals possible future MD county demand for professional petition compliance. | W62: https://www.wypr.org/wypr-news/2026-07-23/how-frederick-countys-first-citizen-led-referendum-failed-in-court | X62: https://hoodline.com/2026/06/frederick-data-center-brawl-crashes-into-maryland-s-high-court/ | AA62: Pass 2 (gap-fill) | AB62: 46319
A63: P062 | B63: Massachusetts | C63: Northeast | D63: Statewide | E63: SignatureDrive.com 'speculative' 2028 petitions (incl. 26-06 legislative employee bargaining and 26-12 end gas tax) | F63: Harold Hubschman filed about 10 questions for 2028 (examples: let legislative staffers unionize; eliminate the gas tax) to pitch to potential backers | G63: Indirect initiative statutes (2028 statewide ballot) | H63: No backer identified. Boston Globe (Sept 22, 2026): Hubschman 'hasn't actually gotten anyone to pick up the proposals' | I63: SignatureDrive.com (Harold Hubschman) is the filer and would be the firm | J63: Active – paid unconfirmed | K63: 74,574 each | L63: Nov 18, 2026 to local clerks; Dec 2, 2026 to Secretary of State | M63: 46344 | N63: =IF(M63="","",M63-'Read Me'!$B$30) -> 25 | O63: unknown | P63: unknown | Q63: unknown | R63: No 2028 spend reported. For 2026-cycle context, SignatureDrive.com took in at least $4.6M since the start of 2025 (incl. >$1M from CPCS union committee; >$1.4M from Legalize Starter Homes, paid to the firm or others) | S63: Harold Hubschman, SignatureDrive.com | T63: unknown | U63: https://signaturedrive.com (named in Boston Globe; site not checked) | V63: The Globe names only 2 of the 10 topics; which certified numbers are Hubschman's beyond 26-06 and 26-12 is unverified. With no paying client as of Sept 22, 2026, these may not circulate at scale. | W63: https://www.bostonglobe.com/2026/09/22/newsletters/harold-hubschman-ballot-questions-signatures-the-scrum/ | X63: https://foleyhoag.com/news-and-insights/blogs/state-ag-insights/2026/september/initial-massachusetts-2028-ballot-questions-target-taxes-technology-and-energy/ | AA63: Pass 2 (gap-fill) | AB63: 46319
A64: P063 | B64: Massachusetts | C64: Northeast | D64: Statewide | E64: Initiative Petition 26-02: income tax rate 5% to 4% by tax year 2031 (2028 ballot) | F64: Cut personal income tax rate from 5.00% to 4.00% over three years (4.67% 2029, 4.33% 2030, 4.00% from 2031) | G64: Indirect initiated state statute (2028 ballot) | H64: Brian Shortsleeve (listed proponent on AG filing). The 2026 version was backed by Taxpayers for an Affordable Massachusetts (spokesperson Chris Keohan), which hinted at a 2028 retry; whether that committee is running 26-02 is unknown | I64: unknown | J64: Active – paid unconfirmed | K64: 74,574 (first round); additional round if Legislature does not act (2026-cycle figure was 12,429; 2028 figure unknown) | L64: Nov 18, 2026 to local election officials; Dec 2, 2026 to Secretary of the Commonwealth | M64: 46344 | N64: =IF(M64="","",M64-'Read Me'!$B$30) -> 25 | O64: unknown | P64: unknown | Q64: unknown | R64: unknown. Shortsleeve paid Hubschman's SignatureDrive tens of thousands of dollars as a 2026 candidate (Boston Globe) | S64: Brian Shortsleeve (proponent) | T64: unknown | U64: unknown | V64: The AG certified it (Foley Hoag, Sept 2026). The 2026 version of this tax cut collected signatures but the SJC removed it from the ballot in June 2026, and Shortsleeve vowed to restart the effort. No source found showing that 2028 collection is underway or that a firm has been hired. Hubschman also filed a near-identical version (26-13), which was not certified. This is the most likely well-funded 2028 drive. | W64: https://foleyhoag.com/news-and-insights/blogs/state-ag-insights/2026/september/initial-massachusetts-2028-ballot-questions-target-taxes-technology-and-energy/ | X64: https://www.mass.gov/info-details/ballot-initiatives-submitted-for-the-2028-biennial-statewide-election-proposed-laws-and-2030-biennial-statewide-election-proposed-constitutional-amendments | Y64: https://www.wbur.org/news/2026/06/19/mass-income-tax-ballot-question-world-cup | Z64: https://www.bostonglobe.com/2026/09/22/newsletters/harold-hubschman-ballot-questions-signatures-the-scrum/ | AA64: Pass 1 + Pass 2 | AB64: 46319
A65: P064 | B65: Massachusetts | C65: Northeast | D65: Statewide | E65: Initiative Petition 26-08: data center regulation (2028 ballot) | F65: Require local voter approval and other conditions (electricity supply contracts, financial guarantees) for data center permits | G65: Indirect initiated state statute (2028 ballot) | H65: Jim Fleming, West Springfield (individual activist) | I65: unknown. Boston.com reports Fleming is tied to JEF Associates, which provides certified signatures and ballot-initiative services; not confirmed as the vendor for this drive | J65: Active – paid unconfirmed | K65: 74,574 (first round); about 12,500 more if the Legislature does not act | L65: Nov 18, 2026 to local election officials; Dec 2, 2026 to Secretary of the Commonwealth | M65: 46344 | N65: =IF(M65="","",M65-'Read Me'!$B$30) -> 25 | O65: unknown | P65: unknown | Q65: unknown | R65: unknown; no funding source identified | S65: Jim Fleming | T65: unknown | U65: unknown | V65: Certified per Foley Hoag. Ballotpedia calls it the nation's second statewide data-center measure. There is no evidence of funding or paid circulation. Possible prospect: environmental or anti-data-center groups would be natural funders. | W65: https://www.boston.com/news/local-news/2026/08/26/a-new-ballot-initiative-takes-aim-at-massachusetts-data-centers/ | X65: https://news.ballotpedia.org/2026/08/13/massachusetts-initiative-would-require-local-voter-approval-and-other-conditions-for-data-center-permits-the-second-statewide-proposal-following-ohio/ | Y65: https://foleyhoag.com/news-and-insights/blogs/state-ag-insights/2026/september/initial-massachusetts-2028-ballot-questions-target-taxes-technology-and-energy/ | Z65: https://www.mass.gov/info-details/ballot-initiatives-submitted-for-the-2028-biennial-statewide-election-proposed-laws-and-2030-biennial-statewide-election-proposed-constitutional-amendments | AA65: Pass 1 + Pass 2 | AB65: 46319
A66: P065 | B66: Massachusetts | C66: Northeast | D66: Statewide | E66: Other AG-certified 2028 petitions: 26-01, 26-05, 26-09, 26-10, 26-11, 26-14, 26-15, 26-16, 26-17, 26-18 | F66: 10 certified proposed laws: collective bargaining for state employees (26-05) and legislative employees (26-06); 1% internet ad tax for social-media safety (26-09); clean-energy tax credit (26-10); eliminate legislative stipends (26-11); end state gas tax (26-12); 2.5% per-parcel property tax cap, versions A and B (26-14, 26-15); larceny over $250 a felony (26-16); sales tax cut from 6.25% to 5% (26-17) | G66: Indirect initiated state statutes (2028 ballot) | H66: Harold Hubschman (filer). As of Sept 22, 2026, the Boston Globe reported that no group had taken up any of these proposals | I66: SignatureDrive.com (Hubschman's firm) would be the natural vendor, but it is not confirmed collecting on these | J66: Active – paid unconfirmed | K66: 74,574 each (first round) | L66: Nov 18, 2026 to local election officials; Dec 2, 2026 to Secretary of the Commonwealth | M66: 46344 | N66: =IF(M66="","",M66-'Read Me'!$B$30) -> 25 | O66: unknown | P66: unknown | Q66: unknown | R66: No 2028 spend found. SignatureDrive.com has taken in at least $4.6M since the start of 2025 from ballot committees and candidates (Boston Globe) | S66: Harold Hubschman, SignatureDrive.com (Brookline, MA) | T66: unknown (signaturedrive.com could not be fetched) | U66: https://www.signaturedrive.com/ (named in the Boston Globe; not fetched) | V66: A signature-firm owner filed these as products he can pitch to funders. 26-07 and 26-13 were filed but not certified. Any of the 10 could become a paid drive if a funder buys in before Nov 18. These are prime prospects for a petition-management pitch: the measures are certified but have no client yet. | W66: https://foleyhoag.com/news-and-insights/blogs/state-ag-insights/2026/september/initial-massachusetts-2028-ballot-questions-target-taxes-technology-and-energy/ | X66: https://www.mass.gov/info-details/ballot-initiatives-submitted-for-the-2028-biennial-statewide-election-proposed-laws-and-2030-biennial-statewide-election-proposed-constitutional-amendments | Y66: https://www.bostonglobe.com/2026/09/22/newsletters/harold-hubschman-ballot-questions-signatures-the-scrum/ | AA66: Pass 1 + Pass 2 | AB66: 46319
A67: P066 | B67: Massachusetts | C67: Northeast | D67: Statewide | E67: Initiatives 26-01 (non-ionizing radiation office) and 26-18 (lifetime license-revocation hardship waiver) (2028) | F67: 26-01: create an Office of Research and Technology Optimization, a public radiation map and fee-based testing. 26-18: hardship license pathway for drivers with lifetime license revocations | G67: Indirect initiated state statutes (2028 ballot) | H67: 26-01: Kirstin Beatty; 26-18: Dale Cluff (listed proponents) | I67: unknown | J67: Active – paid unconfirmed | K67: 74,574 each (first round) | L67: Nov 18, 2026 to local election officials; Dec 2, 2026 to Secretary of the Commonwealth | M67: 46344 | N67: =IF(M67="","",M67-'Read Me'!$B$30) -> 25 | O67: unknown | P67: unknown | Q67: unknown | R67: unknown | S67: Kirstin Beatty; Dale Cluff | T67: unknown | U67: unknown | V67: Both were filed by individuals and certified. No evidence of funding, a committee or paid circulators. Probably volunteer-only or dormant (inference). Low-probability prospects. | W67: https://www.mass.gov/info-details/ballot-initiatives-submitted-for-the-2028-biennial-statewide-election-proposed-laws-and-2030-biennial-statewide-election-proposed-constitutional-amendments | X67: https://foleyhoag.com/news-and-insights/blogs/state-ag-insights/2026/september/initial-massachusetts-2028-ballot-questions-target-taxes-technology-and-energy/ | AA67: Pass 1 | AB67: 46319
A68: P067 | B68: Massachusetts | C68: Northeast | D68: Statewide | E68: Labor Unions for Public Counsel Workers Rights – 2026 initiative | F68: Collective bargaining for public counsel (public defender) workers (inferred from committee name) | G68: Indirect initiated state statute (2026 cycle) | H68: Labor Unions for Public Counsel Workers Rights | I68: unknown | J68: Completed/Expired | K68: 74,574 + 12,429 | L68: Completed | N68: =IF(M68="","",M68-'Read Me'!$B$30) | O68: unknown | P68: unknown | Q68: unknown | R68: More than $1M paid for signature gathering (Boston Globe) | S68: unknown | T68: unknown | U68: unknown | V68: Spend figure comes from the Boston Globe's Sept 22, 2026 Scrum newsletter. Ballot outcome and firm not verified here. | W68: https://www.bostonglobe.com/2026/09/22/newsletters/harold-hubschman-ballot-questions-signatures-the-scrum/ | AA68: Pass 1 | AB68: 46319
A69: P068 | B69: Massachusetts | C69: Northeast | D69: Statewide | E69: Vote Yes for Water and Nature – 2026 initiative | F69: Water and nature conservation measure (details not verified) | G69: Indirect initiated state statute (2026 ballot) | H69: Vote Yes for Water and Nature committee | I69: SignatureDrive.com (Harold Hubschman) plus one other firm (unnamed) | J69: Completed/Expired | K69: 74,574 + 12,429 | L69: Completed | N69: =IF(M69="","",M69-'Read Me'!$B$30) | O69: unknown | P69: unknown | Q69: unknown | R69: Nearly $970,000 paid to SignatureDrive and another firm (Boston Globe) | S69: unknown | T69: unknown | U69: unknown | V69: Confirmed paid firm engagement for the 2026 cycle; collection is finished. | W69: https://www.bostonglobe.com/2026/09/22/newsletters/harold-hubschman-ballot-questions-signatures-the-scrum/ | AA69: Pass 1 | AB69: 46319
A70: P069 | B70: Massachusetts | C70: Northeast | D70: Statewide | E70: Legalize Starter Homes – 2026 Question 7 (zoning reform) | F70: Zoning reform to allow starter homes | G70: Indirect initiated state statute (2026 ballot) | H70: Legalize Starter Homes committee | I70: unknown (professional signature gathering confirmed; firm not named in the sources fetched) | J70: Completed/Expired | K70: 74,574 + 12,429 | L70: Completed (Dec 3, 2025 and July 1, 2026) | M70: 45994 | N70: =IF(M70="","",M70-'Read Me'!$B$30) -> -325 | O70: unknown | P70: unknown | Q70: unknown | R70: More than $1.4M paid for signature gathering (Boston Globe, Sept 2026); about $1.3M professional signature gathering cited by State House News Service (Feb 2026) | S70: unknown | T70: unknown | U70: unknown | V70: The drive is finished and the measure is on the Nov 3, 2026 ballot as Question 7. It is the largest documented MA paid signature spend this cycle and a benchmark for pricing a 2028 statewide drive at roughly $1.3M to $1.4M. | W70: https://www.bostonglobe.com/2026/09/22/newsletters/harold-hubschman-ballot-questions-signatures-the-scrum/ | X70: https://bankerandtradesman.com/rent-control-foes-say-grassroots-claims-about-ballot-question-were-misleading | AA70: Pass 1 | AB70: 46319
A71: P070 | B71: Massachusetts | C71: Northeast | D71: Statewide | E71: Referendum to repeal/suspend 2026 abortion law (Compassionate Care Coalition) | F71: Repeal (and suspend until the vote) the abortion law Gov. Healey signed Aug 10, 2026, which removes restrictions on abortions after 24 weeks | G71: Veto referendum (2028 ballot) | H71: Compassionate Care Coalition: Massachusetts Citizens for Life (president Myrna Maloney Flynn) and Massachusetts Family Action (Sam Miele, coalition chair) | I71: unknown | J71: Completed/Expired | K71: 37,289 to place on the 2028 ballot; 49,719 to suspend the law until the vote | L71: Oct 23, 2026 to local election officials (passed); Nov 6, 2026 to Secretary of the Commonwealth | M71: 46318 | N71: =IF(M71="","",M71-'Read Me'!$B$30) -> -1 | O71: unknown | P71: unknown | Q71: unknown | R71: unknown | S71: Sam Miele (coalition chair, Massachusetts Family Action); Myrna Maloney Flynn (MCFL) | T71: unknown (no coalition website listed; parent orgs Massachusetts Citizens for Life and Massachusetts Family Action/Massachusetts Family Institute have their own sites) | U71: https://masscitizensforlife.org ; https://mafamilyaction.org (sponsor orgs) | V71: Filed Sept 1, 2026. The fall circulation window to local clerks closed Oct 23, 2026, the day before this check, so it is marked completed for collection. The result (count submitted, whether it suspends the law, any emergency preamble from Healey) is unknown. No source states whether circulators were paid or volunteer. Next action: the Nov 6 filing with the Secretary of the Commonwealth. | W71: https://www.wbur.org/news/2026/09/04/massachusetts-abortion-law-2028-refendum | X71: https://wbsm.com/massachusetts-abortion-law-repeal-2028/ | Y71: https://www.liveaction.org/news/massachusetts-group-seeks-overturn-abortion-law | Z71: https://commonwealthbeacon.org/health-care/opponents-of-new-abortion-law-eye-2028-repeal-effort/; https://www.statehousenews.com/news/healthcare/healey-noncommittal-on-shielding-new-law-for-abortions-later-in-pregnancy/article_ca18c182-6bc3-4841-98be-d544b5659827.html | AA71: Pass 1 + Pass 2 | AB71: 46319
A72: P071 | B72: Massachusetts | C72: Northeast | D72: Statewide | E72: MA circulator job ads (The Outreach Team for Coalition for Healthy Democracy / Protect Democracy) | F72: Hourly-paid petition circulator crews for Massachusetts initiatives (2024–2026 cycles) | G72: Initiative signature gathering (vendor hiring) | H72: Coalition for Healthy Democracy (per job ads) | I72: The Outreach Team; Movement Builders | J72: Completed/Expired | K72: n/a | L72: n/a | N72: =IF(M72="","",M72-'Read Me'!$B$30) | O72: n/a | P72: Aug 26, 2025 Movement Builders ad (Amherst): $20/hr circulator, $22/hr team lead, plus bonuses and overtime. The Outreach Team (Boston): $21/hr circulator, $23/hr team lead, daily bonuses up to $170 (posting closed). Earlier ads: $19–21/hr, bonuses of $50–200/day | Q72: https://careers.arena.run/companies/movement-builders/jobs/57300666-petition-circulator | R72: unknown | S72: unknown | T72: https://www.theoutreachteam.net/interest-form-tot | U72: https://careers.arena.run/companies/the-outreach-team-2 | V72: These are the only MA circulator pay rates found. The newest is from Aug 2025 (2026 cycle). No fall-2026 posting for 2028 petitions was found. These hourly rates are a useful benchmark against the per-signature model the Legislature is considering banning (Finegold bill). | W72: https://careers.arena.run/companies/the-outreach-team-2/jobs/58881847-petitioner-work-to-protect-democracy | X72: https://jobs.recorder.com/job/970cd2a6-5876-445f-a3c7-cf1d31536102/petition-circulator | Y72: https://jobs.gazettenet.com/job/92b385da-b99a-48cd-b22e-9281f552447e/support-staff-protect-democracy | Z72: https://www.ziprecruiter.com/Jobs/Petition; https://careers.arena.run/companies/movement-builders/jobs/57300666-petition-circulator; https://app.massnonprofitnet.org/jobs/petitioners-needed-campaign-for-psilocybin-access | AA72: Pass 1 + Pass 2 | AB72: 46319
A73: P072 | B73: Michigan | C73: Central | D73: Statewide (2028) | E73: Rank MI Vote ranked-choice voting amendment, 2028 relaunch | F73: Constitutional amendment for ranked-choice voting and election overhaul | G73: Statewide constitutional amendment initiative | H73: Rank MI Vote | I73: None (volunteer-driven in 2025-26) | J73: Upcoming | K73: unknown | L73: Planned 'second launch in April 2027' for 2028 ballot | N73: =IF(M73="","",M73-'Read Me'!$B$30) | O73: unknown | P73: N/A (volunteer) | Q73: unknown | R73: unknown | S73: Rank MI Vote co-directors (names unknown) | T73: unknown | U73: unknown | V73: Ended its 2026 effort in Dec 2025. Its failure as an all-volunteer drive makes it a natural prospect to pitch a paid operation for 2027-28. | W73: https://bridgemi.com/michigan-government/michigan-ranked-choice-voting-group-ends-2026-ballot-effort/ | AA73: Pass 2 (gap-fill) | AB73: 46319
A74: P073 | B74: Michigan | C74: Central | D74: Mason (Ingham County) | E74: Recall of Mason Mayor Russell Whipple (data center) | F74: Recall mayor over handling of proposed data center | G74: Municipal recall | H74: Michigan Citizens Against Data Centers (spokesperson Paula Caltrider) | I74: unknown (appears volunteer) | J74: Upcoming | K74: unknown | L74: Targeting May 2027 ballot; refiling required | N74: =IF(M74="","",M74-'Read Me'!$B$30) | O74: First petition rejected (language mismatch) | P74: unknown | Q74: unknown | R74: unknown | S74: Paula Caltrider | T74: unknown | U74: unknown | V74: The companion recall of Councilwoman Elaine Ferris is on the Nov 3, 2026 ballot (Newsweek). Other Michigan township data-center recalls (Augusta, Frenchtown, Lowell, Van Buren, Lenox) were ongoing or had unclear status as of summer 2026. Lyon Township failed. | W74: https://www.wkar.org/election-2026/2026-07-08/recall-effort-continues-against-city-of-mason-mayor | X74: https://www.newsweek.com/elected-officials-face-recalls-nationwide-data-center-support-12400196 | AA74: Pass 2 (gap-fill) | AB74: 46319
A75: P074 | B75: Michigan | C75: Great Lakes | D75: Statewide | E75: Americans for Citizen Voting – Michigan (citizens-only voting / voter ID amendment), 2028 revival | F75: Constitutional amendment requiring citizenship verification for voters, a statewide voter identity verification program, and elimination of the affidavit option for voters without photo ID | G75: Initiated constitutional amendment (2028 target) | H75: Americans for Citizen Voting – Michigan (chair Paul Jacob; organizer Kurt O'Keefe); backed by Virginia-based Liberty Initiative Fund | I75: unknown for 2028. In the 2026 drive ACV paid Campaign & Petition Management (Colorado, ~$3M), Campaign Audit & Trust (Ludington, ~$200K) and Victory Field Operations (Webberville, $35K), per campaign finance records as of Oct 20, 2025 | J75: Upcoming | K75: unknown for 2028 (446,198 valid was the 2026 threshold; the 2028 threshold depends on the 2026 governor vote) | L75: unknown (2028 cycle) | N75: =IF(M75="","",M75-'Read Me'!$B$30) | O75: 0 for 2028 cycle (unknown); 2026 drive filed 750,000+ | P75: unknown | Q75: unknown | R75: 2026 drive: ~$3.2M+ paid to petition vendors as of Oct 2025; 2028 budget unknown | S75: Paul Jacob (chair) | T75: unknown | U75: unknown | V75: Sept 10, 2026 Michigan Advance: Jacob said the group will return in 2028 with far more signatures than the minimum. Oct 14, 2026 coverage repeats the 2028 aim. No 2028 petition form approval, vendor contract or hiring found yet. Most likely large paid drive in the region for 2028, given the 2026 spending history. Pending state bills to ban per-signature pay passed the Senate in Nov 2025 but are not law per the Jan 2026 reporting. | W75: https://michiganadvance.com/?p=111313 | X75: https://www.newsfromthestates.com/node/426976 | Y75: https://www.newsfromthestates.com/node/432739 | Z75: https://michiganadvance.com/2026/09/10/citizens-only-voting-petition-sponsors-look-to-2028-after-initiative-fails-before-state-canvassers/; https://bridgemi.com/?p=71740; https://www.votebeat.org/michigan/2026/01/20/petition-signature-gathering-lying-ballot-questions-constitutional-amendments/ | AA75: Pass 1 + Pass 2 | AB75: 46319
A76: P075 | B76: Michigan | C76: Great Lakes | D76: Statewide | E76: Americans for Citizen Voting – 2026 proof-of-citizenship amendment drive | F76: Same as above, for the Nov 2026 ballot | G76: Initiated constitutional amendment | H76: Americans for Citizen Voting – Michigan | I76: Campaign & Petition Management (Colorado); Campaign Audit & Trust (Ludington, MI); Victory Field Operations (Webberville, MI) | J76: Completed/Expired | K76: 446,198 valid | L76: July 6, 2026 | M76: 46209 | N76: =IF(M76="","",M76-'Read Me'!$B$30) -> -110 | O76: 750,000+ filed (per sponsor); failed in sampling by a few signatures; Board of State Canvassers deadlocked 2-2 | P76: unknown (articles cite a ~$15/signature 2024 national average from Ballotpedia, not a Michigan rate) | Q76: unknown | R76: ~$3M to Campaign & Petition Management, ~$200K to Campaign Audit & Trust, $35K to Victory Field Operations (as of Oct 20, 2025) | S76: Paul Jacob (chair); consultant Kristin Combs (said she does not manage vendors) | T76: unknown | U76: unknown | V76: Confirmed paid drive (vendor payments in campaign finance; ACV says 700+ people collected). Michigan Supreme Court ruled against it and it is off the 2026 ballot. | W76: https://bridgemi.com/?p=71740 | X76: https://www.votebeat.org/michigan/2026/01/20/petition-signature-gathering-lying-ballot-questions-constitutional-amendments/ | Y76: https://michiganadvance.com/2026/08/24/board-of-state-canvassers-deadlocks-on-citizens-only-voting-measure-setting-up-court-fight/ | Z76: https://www.michiganpublic.org/politics-government/2026-09-04/michigans-november-2026-ballot-is-official-includes-two-questions-for-all-voters | AA76: Pass 1 | AB76: 46319
A77: P076 | B77: Michigan | C77: Great Lakes | D77: Statewide | E77: Michiganders for Money Out of Politics (now Proposal 2, Nov 2026) | F77: Initiated statute barring regulated utilities and large government contractors from making campaign contributions | G77: Initiated statute (went to the ballot after the legislature did not adopt it) | H77: Michiganders for Money Out of Politics (steering committee co-chair Christy McGillivray); circulator training material hosted by Voters Not Politicians | I77: unknown | J77: Completed/Expired | K77: 356,958 valid | L77: May 27, 2026 (filed in May) | M77: 46169 | N77: =IF(M77="","",M77-'Read Me'!$B$30) -> -150 | O77: 562,000+ submitted; Board of State Canvassers found sufficient (sample 657/1,000 valid after challenge) | P77: unknown | Q77: unknown | R77: unknown | S77: Christy McGillivray (co-chair) | T77: unknown | U77: unknown | V77: Qualified as Proposal 2. Volunteer circulator listings (Idealist, VNP) found; no paid vendor found in what I checked. Suspended 2026 MI drives (not separate records): Rank MI Vote (Dec 2025), Invest in MI Kids (Mar 2026), Voters to Stop Paycuts (Mar 2026); AxMITax was volunteer-only. | W77: https://michiganadvance.com/2026/07/24/board-of-state-canvassers-finds-michigans-money-out-of-politics-effort-has-sufficient-valid-signatures/ | X77: https://www.michiganpublic.org/politics-government/2026-09-04/michigans-november-2026-ballot-is-official-includes-two-questions-for-all-voters | Y77: https://bridgemi.com/michigan-government/michigan-petition-groups-begin-final-push-what-will-make-the-ballot/ | Z77: https://www.idealist.org/en/volunteer-opportunity/fb8c4254c5774729b3bee90331de9ade-michiganders-for-money-out-of-politics-petition-circulator-voters-not-politicians-lansing | AA77: Pass 1 | AB77: 46319
A78: P077 | B78: Minnesota | C78: Plains/Texas | D78: Statewide / local | E78: Local referendum/recall/charter petitions | F78: n/a | G78: n/a | H78: n/a | I78: n/a | J78: No verified project | K78: n/a | L78: n/a | N78: =IF(M78="","",M78-'Read Me'!$B$30) | O78: n/a | P78: unknown | Q78: unknown | R78: unknown | S78: n/a | T78: n/a | U78: n/a | V78: Minnesota has no statewide citizen initiative. City charter petitions (e.g. Minneapolis, St. Paul), recalls and ballot access were NOT searched because the shared web-search budget ran out. This is a research gap, not a confirmed absence. | W78: https://www.minneapolismn.gov/government/boards-and-commissions/charter-commission/amending-the-charter/ | X78: https://www.kwit.org/podcast/spm-news/2026-02-16/spencer-iowa-residents-force-special-election-for-city-council-post | AA78: Pass 1 + Pass 2 | AB78: 46319
A79: P078 | B79: Mississippi | C79: Southeast | D79: Statewide | E79: NO VERIFIED ACTIVE PAID PROJECT | F79: Statewide initiative process (still not restored) and ballot access | G79: Statewide initiative (not available) | H79: unknown | I79: unknown | J79: No verified project | K79: Proposed SCR 518 would require 10% of registered voters (~170,000); not in effect. Independent statewide candidate: 1,000 (due Feb 2, 2026). | L79: unknown | N79: =IF(M79="","",M79-'Read Me'!$B$30) | O79: unknown | P79: unknown | Q79: unknown | R79: unknown | S79: unknown | T79: unknown | U79: unknown | V79: Mississippi's initiative process has not been confirmed restored. SCR 518 (Sen. Jeremy England) passed the Senate Elections Committee in Feb 2026. It would allow statutory-only initiatives, exclude abortion and PERS, and needs two-thirds of the Senate by Feb 12 plus House action and a statewide vote. Its final 2026 outcome could not be confirmed before the search budget ran out. Even if adopted, it requires voter ratification, so no initiative drive is possible yet. | W79: https://mississippitoday.org/2026/02/04/senate-measure-to-restore-mississippi-voters-right-to-ballot-initiative-advances/ | X79: https://ballot-access.org/2026/06/22/june-2026-ballot-access-news-print-edition/ | AA79: Pass 1 | AB79: 46319
A80: P079 | B80: Missouri | C80: Plains/Texas | D80: Statewide | E80: Missouri Right to Education constitutional amendment, 2028 return | F80: Constitutional amendment making public education a fundamental right | G80: Statewide constitutional initiative, 2028 | H80: Missouri Right to Education campaign (director Spencer Toder); Missouri NEA pledged 'substantial support' for 2028 | I80: unknown | J80: Upcoming | K80: Constitutional threshold: 8% of the gubernatorial vote in 6 of 8 congressional districts (exact 2028 figure unknown) | L80: unknown (2028 cycle; Missouri initiative deadlines are typically early May of the election year) | N80: =IF(M80="","",M80-'Read Me'!$B$30) | O80: About 35,000 in the abandoned 2026 attempt; 2028 count 0 | P80: unknown | Q80: unknown | R80: unknown | S80: Spencer Toder; Missouri NEA (budget source) | T80: unknown | U80: unknown | V80: The 2026 drive was volunteer-led and stopped Mar 31, 2026 at roughly one-fifth of the needed signatures. The campaign plans to return in 2028 with MNEA backing. MNEA money makes this a candidate for a paid drive, but nothing is confirmed. The SOS 2028 petition page could not be fetched (not on the allowlist), so 2028 filing status is unknown. | W80: https://missouriindependent.com/2026/03/31/missouri-public-education-amendment-campaign-stops-signature-push-plans-2028-return/ | AA80: Pass 1 + Pass 2 | AB80: 46319
A81: P080 | B81: Missouri | C81: Plains/Texas | D81: Statewide | E81: Respect MO Voters (Amendment 6) | F81: Require an 80% legislative vote plus a statewide vote to change voter-approved initiatives; bar the legislature from restricting the initiative process | G81: Statewide constitutional initiative, 2026 | H81: Respect MO Voters campaign | I81: unknown | J81: Completed/Expired | K81: 5% of the gubernatorial vote in 6 of 8 congressional districts (~170,215 minimum depending on distribution) | L81: May 3, 2026 (submitted) | M81: 46145 | N81: =IF(M81="","",M81-'Read Me'!$B$30) -> -174 | O81: More than 367,000 (submitted) | P81: unknown | Q81: unknown | R81: unknown (MEC filings not checked) | S81: unknown | T81: unknown | U81: unknown | V81: This was the only citizen initiative to submit signatures for Missouri's 2026 ballot. The Missouri Supreme Court placed it on the Nov 3 ballot as Amendment 6 (Sept 3, 2026). Firm and pay were not found. | W81: https://news.ballotpedia.org/2026/05/05/signatures-submitted-for-missouri-initiative-requiring-voter-approval-for-certain-legislative-changes-to-initiative-process-and-voter-approved-laws/ | X81: https://www.krcu.org/2026-09-03/missouri-supreme-court-puts-respect-missouri-voters-plan-on-november-ballot | AA81: Pass 1 | AB81: 46319
A82: P081 | B82: Missouri | C82: Central | D82: Independence (Jackson County) | E82: Recall of Councilman John Perkins (data center) | F82: Recall council member over Nebius AI data center tax incentives | G82: Municipal recall | H82: Resident organizers (McKenna Cobb) | I82: unknown | J82: Completed/Expired | K82: About 1,000 | L82: Recall election held Sep 1, 2026 | M82: 46266 | N82: =IF(M82="","",M82-'Read Me'!$B$30) -> -53 | O82: 1,214 certified | P82: unknown | Q82: unknown | R82: unknown | S82: McKenna Cobb | T82: unknown | U82: unknown | V82: Perkins was recalled 68% to 32%. Residents have also called for a data-center moratorium vote. This is a proof case for data-center-opposition petition demand. | W82: https://kctv5.com/2026/06/11/ai-data-center-vote-fuels-recall-push-independence-councilman-now-faces-election-keep-his-seat/ | X82: https://www.kshb.com/news/local-news/independence-mo-councilman-recalled-by-voters-in-his-district-after-his-vote-for-data-center-tax-incentives | AA82: Pass 2 (gap-fill) | AB82: 46319
A83: P082 | B83: Missouri | C83: Central | D83: Statewide (2026 litigation) | E83: Respect MO Voters (Amendment 6) and People Not Politicians redistricting referendum (Prop A) | F83: Respect MO Voters: limit legislative changes to voter-approved initiatives. Prop A: overturn the 2025 congressional map | G83: Constitutional amendment initiative / statutory referendum | H83: Respect MO Voters (co-founder Benjamin Singer); People Not Politicians PAC | I83: unknown | J83: Completed/Expired | K83: Amendment: 8% in 6 of 8 CDs. Referendum: 5% in 6 of 8 CDs | L83: Signature phase done; litigation over Nov 3, 2026 ballot placement (Missouri Supreme Court reportedly ordered an initiative back on ballot per Missouri Times; which one not confirmed here) | M83: 46329 | N83: =IF(M83="","",M83-'Read Me'!$B$30) -> 10 | O83: Prop A: about 305,000 submitted (about 103,000 ruled invalid as gathered before Oct 14). Respect MO Voters: had enough per SOS preliminary reports | P83: unknown | Q83: unknown | R83: unknown | S83: Benjamin Singer; attorney Chuck Hatfield | T83: unknown | U83: unknown | V83: Context only. If Respect MO Voters is defeated or blocked, a 2028 refile is plausible but unverified. No Missouri 2028 petition with paid circulators was found. | W83: https://www.kcur.org/politics-elections-and-government/2026-08-18/missouri-ballot-proposals-respect-mo-voters-redistricting-signatures-blocked | X83: https://themissouritimes.com/breaking-missouri-supreme-court-orders-initiative-petition-back-on-november-ballot/ | AA83: Pass 2 (gap-fill) | AB83: 46319
A84: P083 | B84: Missouri | C84: Plains/Texas | D84: Statewide | E84: People Not Politicians – referendum on 2025 congressional map | F84: Veto referendum to overturn the congressional map passed Sept 12, 2025 | G84: Statewide veto referendum | H84: People Not Politicians (PAC); executive director Richard von Glahn | I84: unknown | J84: Completed/Expired | K84: About 110,000 valid (5% of voters in 6 of 8 congressional districts) | L84: Submitted Dec 9, 2025 | M84: 46000 | N84: =IF(M84="","",M84-'Read Me'!$B$30) -> -319 | O84: 305,968 on 49,773 pages (SOS withheld pre-Oct 14 pages) | P84: unknown | Q84: unknown | R84: unknown | S84: Richard von Glahn | T84: unknown | U84: unknown | V84: Labor Tribune says the drive used paid petition circulators alongside labor volunteers, and that outside groups allegedly offered paid circulators $5,000 to $30,000 to dump signatures. The Missouri Supreme Court put the referendum on the Nov 2026 ballot. The drive is finished. Firm and pay rate were not found. | W84: https://labortribune.com/with-labors-help-305k-signatures-submitted-on-referendum-challenging-missouris-gerrymandered-congressional-maps/ | X84: https://electionlawblog.org/2026/denny-hoskins-isnt-verifying-one-third-of-signatures-for-vote-on-missouris-gerrymandered-map/ | Y84: https://www.democracydocket.com/?p=65068 | Z84: https://www.krcu.org/2026-09-03/missouri-supreme-court-puts-respect-missouri-voters-plan-on-november-ballot | AA84: Pass 1 | AB84: 46319
A85: P084 | B85: Montana | C85: Mountain/Southwest | D85: Statewide | E85: Initiative 194 - prohibit entity political spending | F85: Bar corporations, nonprofits, and trade associations from contributing to candidate and ballot-measure elections | G85: Statewide initiated statute | H85: Transparent Election Initiative | I85: unknown | J85: Completed/Expired | K85: 30,121 plus 5% in 34 of 100 House districts | L85: June 19, 2026 to counties; July 17, 2026 to SOS | M85: 46192 | N85: =IF(M85="","",M85-'Read Me'!$B$30) -> -127 | O85: About 50,000 submitted | P85: unknown | Q85: unknown | R85: unknown (Ballotpedia: 2024 MT qualified initiatives averaged about $1.7M and about $27.42 per required signature) | S85: unknown | T85: unknown | U85: unknown | V85: Paid share unknown. 12 initiatives were filed for 2026 in Montana; only I-194, CI-132, and CI-133 submitted signatures. | W85: https://news.ballotpedia.org/2026/06/17/campaign-behind-a-ballot-initiative-to-prohibit-corporations-from-political-spending-in-montana-submits-signatures/ | AA85: Pass 1 | AB85: 46319
A86: P085 | B86: Montana | C86: Mountain/Southwest | D86: Statewide | E86: CI-133 - initiative and referendum rights in the Declaration of Rights | F86: Guarantee impartial, predictable, transparent initiative processes | G86: Statewide constitutional initiative | H86: Montanans Decide (campaign manager SK Rossi) | I86: unknown | J86: Completed/Expired | K86: 60,241 (10%) plus district distribution | L86: June 19, 2026 to counties; July 17, 2026 to SOS | M86: 46192 | N86: =IF(M86="","",M86-'Read Me'!$B$30) -> -127 | O86: Over 100,000 filed with counties | P86: unknown | Q86: unknown | R86: unknown | S86: SK Rossi (campaign manager) | T86: unknown | U86: unknown | V86: Paid share unknown. CI-132 (nonpartisan judicial elections; sponsor not found) also submitted signatures for 2026. | W86: https://news.ballotpedia.org/2026/06/23/campaign-behind-montana-ballot-measure-to-guarantee-impartial-predictable-transparent-and-expeditious-processes-for-ballot-initiatives-submits-signatures/ | X86: https://sosmt.gov/docs/24/ballot-issues/69573/2025-26_ballot_issues__signature_gathering | AA86: Pass 1 | AB86: 46319
A87: P086 | B87: Nebraska | C87: Plains/Texas | D87: Statewide | E87: Make Nebraska Even Better (15-petition 2028 package) | F87: 15 separate statutory/constitutional initiatives for 2028: property tax levy limits and voter approval to exceed them, ban on unfunded mandates, 'Harvest Fuel Tax Holiday' (2-month annual fuel tax suspension plus 35-cent cap), education and election administration. | G87: Statewide initiatives (statutory and constitutional), 2028 | H87: Eric Underwood (Lincoln, former Nebraska GOP chair) / Advocates for All Nebraskans | I87: A new Nebraska-based signature-gathering firm, name not disclosed, using only Nebraska circulators | J87: Upcoming | K87: Statutory: 7% of registered voters; constitutional: 10% of registered voters; plus 5% in at least 38 of 93 counties (exact counts unknown for 2028) | L87: First week of July 2028 | N87: =IF(M87="","",M87-'Read Me'!$B$30) | O87: 0 (launch planned after the Nov 3, 2026 election) | P87: unknown | Q87: unknown | R87: unknown | S87: Eric Underwood | T87: unknown (no campaign contact published) | U87: unknown | V87: Nebraska Examiner (Oct 16, 2026) reports launch after Nov 3; wording still under Revisor of Statutes review. Plans door-to-door canvassing from a 200,000+ voter list across ~150 cities. Article says a new Nebraska-only signature firm will assist, so paid circulation is likely, but pay is not confirmed. Same group submitted no signatures for its 2026 petitions. Watch for legislation from Gov. Pillen and SOS Evnen to ban per-signature pay and require circulators to be citizens (see 1011now, Sept 3, 2026). | W87: https://www.wowt.com/2026/10/16/antithesis-that-chaos-15-petition-effort-will-soon-launch-seeking-nebraskas-2028-ballot/ | X87: https://www.newsfromthestates.com/node/433107 | AA87: Pass 1 | AB87: 46319
A88: P087 | B88: Nebraska | C88: Plains/Texas | D88: Statewide | E88: Respect Nebraska Voters | F88: Constitutional amendment raising the legislative vote needed to change voter-approved initiatives from 2/3 to 4/5, and applying it to laws affecting the initiative process | G88: Statewide constitutional initiative, 2026 | H88: Respect Nebraska Voters coalition; ballot sponsor Dawn Essink (Omaha Together One Community) | I88: unknown | J88: Completed/Expired | K88: 10% of registered voters plus 5% in 38 counties (exact count not given in the source) | L88: July 2, 2026 | M88: 46205 | N88: =IF(M88="","",M88-'Read Me'!$B$30) -> -114 | O88: More than 186,000 (submitted, campaign figure) | P88: unknown | Q88: unknown | R88: unknown | S88: Dawn Essink (ballot sponsor) | T88: unknown | U88: unknown | V88: Signatures submitted July 2, 2026, with signers in every county. Whether circulators were paid is not stated, and qualification was not confirmed in the sources read. | W88: https://www.wowt.com/2026/07/02/respect-nebraska-voters-submits-more-than-186k-signatures-november-ballot-initiative/ | AA88: Pass 1 | AB88: 46319
A89: P088 | B89: Nebraska | C89: Plains/Texas | D89: Statewide | E89: Tax Relief Nebraska – online sports betting (constitutional + statutory) | F89: Legalize and regulate online sports betting; statutory framework sends 70% of tax proceeds to property tax relief | G89: Statewide initiatives (constitutional amendment + statute), 2026 | H89: Tax Relief Nebraska (led by WarHorse casino with online sportsbook operators and local investors) | I89: unknown | J89: Completed/Expired | K89: ~126,000 (constitutional); ~88,000 (statutory) | L89: July 2, 2026 (submitted about a week early) | M89: 46205 | N89: =IF(M89="","",M89-'Read Me'!$B$30) -> -114 | O89: 201,000+ (constitutional) and ~146,000 (statutory), as submitted, not verified counts | P89: unknown | Q89: unknown | R89: DraftKings and FanDuel gave about $3.5M each (more than $7M combined) per Nebraska Public Media, June 26, 2026 | S89: unknown (Lynne McNally, WarHorse director of government relations, is the public spokesperson) | T89: unknown | U89: unknown | V89: Drive finished with signatures submitted in late June / July 2026. McNally said paid circulators are necessary for a successful drive. Nebraska law allows per-signature pay and out-of-state circulators. Firm name not found; the NADC filings were not checked. Final ballot certification not confirmed in the sources read. | W89: https://www.wowt.com/2026/07/02/backers-online-sports-betting-nebraska-submit-signatures-get-2026-ballot/ | X89: https://nebraskapublicmedia.org/es/news/news-articles/online-gambling-petition-on-track-to-make-nebraskas-ballot-with-multi-million-dollar-campaign/ | Y89: https://www.legalsportsreport.com/268438/nebraska-online-sports-betting-signatures-delivered-before-deadline/ | Z89: https://cdcgaming.com/brief/nebraska-online-sports-betting-ballot-push-clears-signature-threshold/ | AA89: Pass 1 | AB89: 46319
A90: P089 | B90: Nevada | C90: West | D90: Statewide | E90: Protect Girls' Sports constitutional initiative (possible refile) | F90: Bar transgender girls from girls' school sports divisions | G90: Initiative constitutional amendment | H90: Protect Girls' Sports PAC (backed by Gov. Joe Lombardo) | I90: unknown | J90: Upcoming | K90: 148,788 (split across 4 congressional districts), per Nevada Current | L90: unknown (2026 attempt dropped; refile date not announced) | N90: =IF(M90="","",M90-'Read Me'!$B$30) | O90: unknown | P90: unknown | Q90: unknown | R90: unknown | S90: Gov. Joe Lombardo / Protect Girls' Sports PAC | T90: unknown | U90: unknown | V90: Lombardo dropped the 2026 petition despite winning in the NV Supreme Court on June 18, citing legal delays. He asked the 2027 Legislature to act and vowed to bring the petition back if it doesn't. No current signature collection was found. | W90: https://nevadacurrent.com/?p=219001 | X90: https://nevadacurrent.com/?p=219689 | AA90: Pass 2 (gap-fill) | AB90: 46319
A91: P090 | B91: Nevada | C91: West | D91: Statewide | E91: Vote Nevada PAC - redistricting / Voters' Bill of Rights / unfunded-mandate fix / digital signatures | F91: Nonpartisan redistricting, open primaries, and initiative-process reforms | G91: Initiative constitutional amendments and a statutory initiative | H91: Vote Nevada PAC (Sondra Cosgrove, Doug Goodman) | I91: None (volunteer) | J91: Completed/Expired | K91: About 148,788 each (constitutional) | L91: 2026-06-24 (passed) | M91: 46197 | N91: =IF(M91="","",M91-'Read Me'!$B$30) -> -122 | O91: Insufficient (none qualified) | P91: unknown | Q91: unknown | R91: No funding disclosures as of Oct 2025; lacked funds to appeal court losses | S91: Sondra Cosgrove | T91: unknown | U91: unknown | V91: Volunteers could not gather enough physical signatures, a judge struck the redistricting measure as an unfunded mandate, and the digital-signature measure was withdrawn after a challenge from BizPAC. This is a funded-infrastructure gap: the group may refile for 2028 (not announced). Only 2 statewide questions (Q6, Q7, both legislative second votes) are on NV's Nov 2026 ballot. No 2028 initiative filings or active county/city petitions or recalls were verified. The recalls found were 2020 or older. | W91: https://thenevadaindependent.com/article/tracking-2026-nevada-ballot-measures-whats-up-for-a-vote-and-whats-still-in-limbo | X91: https://nevadacurrent.com/?p=219689 | AA91: Pass 2 (gap-fill) | AB91: 46319
A92: P091 | B92: New Hampshire | C92: Northeast | D92: Statewide/local | E92: No verified project | F92: n/a | G92: n/a | H92: n/a | I92: n/a | J92: No verified project | K92: n/a | L92: n/a | N92: =IF(M92="","",M92-'Read Me'!$B$30) | O92: n/a | P92: n/a | Q92: n/a | R92: n/a | S92: n/a | T92: n/a | U92: n/a | V92: Not researched: the shared web-search budget (200 searches per turn) ran out before NH searches could run. Background: NH has no statewide citizen initiative, so look for local petitioned warrant articles (March 2027 town meetings, typically filed in Jan–Feb) and candidate nomination petitions. Needs a follow-up pass. | W92: https://www.salemnh.gov/DocumentCenter/View/6408/Submitttal-Guidelines-for-Citizen-Petition-Warrant-Articles---2026 | AA92: Pass 1 + Pass 2 | AB92: 46319
A93: P092 | B93: New Jersey | C93: Northeast | D93: Statewide/local | E93: No verified project | F93: n/a | G93: n/a | H93: n/a | I93: n/a | J93: No verified project | K93: n/a | L93: n/a | N93: =IF(M93="","",M93-'Read Me'!$B$30) | O93: n/a | P93: n/a | Q93: n/a | R93: n/a | S93: n/a | T93: n/a | U93: n/a | V93: Not researched: search budget exhausted. The likely market is municipal initiative/referendum petitions and 2027 legislative-primary candidate petitions. Needs a follow-up pass. | W93: https://insidernj.com/press-release/hoboken-rent-control-referendum-petitions-submited-to-clerk-for-certification-clock-starts-ticking-on-special-election | AA93: Pass 1 + Pass 2 | AB93: 46319
A94: P093 | B94: New Mexico | C94: Mountain/Southwest | D94: Statewide | E94: New Mexico Forward Party - minor-party candidate ballot access (Perls for U.S. Senate; Vigil for State Auditor) | F94: Put Forward Party candidates on the 2026 ballot | G94: Candidate / minor-party ballot access petition | H94: New Mexico Forward Party (chair Bob Perls) | I94: unknown | J94: Completed/Expired | K94: More than 14,000 per minor-party candidate | L94: Passed; lawsuit lost at district court and 10th Circuit (Sept 2026); SCOTUS emergency request filed Sept 15, 2026 | M94: 46280 | N94: =IF(M94="","",M94-'Read Me'!$B$30) -> -39 | O94: unknown (fell short of 14,000; party says it exceeded major-party thresholds) | P94: unknown | Q94: unknown | R94: unknown | S94: Bob Perls (party chair) | T94: unknown | U94: unknown | V94: This shows unmet demand for minor-party ballot access work in New Mexico (a 14K+ signature bar). Whether any circulators were paid is unknown. | W94: https://sourcenm.com/2026/09/16/new-mexico-forward-party-asks-us-supreme-court-to-intervene-in-ballot-access-lawsuit/ | AA94: Pass 1 | AB94: 46319
A95: P094 | B95: New York | C95: Northeast | D95: Statewide / NYC | E95: 2027 candidate designating and independent nominating petitions (NYC Council, local offices) | F95: Ballot access for 2027 primary/general candidates | G95: Candidate ballot access petitions | H95: Candidates and party committees (various) | I95: unknown | J95: Upcoming | K95: Per NY Election Law 6-136 by office (not verified for 2027) | L95: unknown — the 2027 NYS political calendar was not found; the brief's estimate is that petitioning starts around late Feb 2027 | N95: =IF(M95="","",M95-'Read Me'!$B$30) | O95: n/a | P95: unknown for 2027. Benchmark: Green Party of NY paid $25/hr in 2024 (5 weeks) | Q95: unknown | R95: unknown | S95: Individual campaigns | T95: NYS Board of Elections / NYC Board of Elections (vote.nyc) | U95: https://elections.ny.gov ; https://vote.nyc | V95: No 2027 calendar or 2027 job ads verified. NY has no statewide citizen initiative. The paid-petitioning market is candidate ballot access, concentrated Feb-Apr. Bills S6996/A1223 (2025) affecting petitioning exist, but their content was not verified. | W95: https://codes.findlaw.com/ny/election-law/eln-sect-6-136/ | X95: https://www.gp.org/gpny_now_hiring_petition_circulators | AA95: Pass 2 (gap-fill) | AB95: 46319
A96: P095 | B96: North Carolina | C96: Southeast | D96: Statewide | E96: North Carolina Forward Party - new party recognition petition (2027-28) | F96: Gain statewide party ballot status | G96: Party ballot access petition | H96: Forward Party | I96: unknown | J96: Active – paid unconfirmed | K96: 14,310 (2026 requirement; the 2028 figure may differ) | L96: unknown for 2027/2028 (the 2026 deadline was May 17, 2026) | M96: 46159 | N96: =IF(M96="","",M96-'Read Me'!$B$30) -> -160 | O96: unknown. Not enough for 2026; the party said it will use the signatures for 2027 and 2028. | P96: unknown | Q96: unknown | R96: unknown | S96: Patrick Newton, chair | T96: unknown | U96: unknown | V96: Per Ballot Access News June 2026, Forward is continuing its NC party petition into 2027-2028. Libertarian and Green are already qualified; NC statewide independent needs 83,874. No evidence that the circulators are paid. | W96: https://ballot-access.org/?p=93821 | X96: https://www.wunc.org/politics/2025-07-28/nc-forward-party-campaign-ballot | Y96: https://ncsbe.gov/candidates/petitions/petition-recognition-political-party | Z96: https://ballot-access.org/2026/06/22/june-2026-ballot-access-news-print-edition/ | AA96: Pass 1 + Pass 2 | AB96: 46319
A97: P096 | B97: North Dakota | C97: Plains/Texas | D97: Statewide | E97: NO VERIFIED ACTIVE PAID PROJECT | F97: n/a | G97: n/a | H97: n/a | I97: n/a | J97: No verified project | K97: n/a | L97: n/a | N97: =IF(M97="","",M97-'Read Me'!$B$30) | O97: n/a | P97: unknown | Q97: unknown | R97: unknown | S97: n/a | T97: n/a | U97: https://www.sos.nd.gov/elections/voter/ballot-measures/petitions-circulation | V97: The ND SOS 'Petitions in Circulation' page shows 'None at this time' for initiated measures, referred measures and petitions under review. The SOS news page (Sept 21, 2026) mentions only the Nov 3 ballot guide. The 2026 general ballot has CM1 (HCR 3003, legislative) and CM2 (school lunch funding). Local and recall petitions were not searched. | W97: https://www.sos.nd.gov/elections/voter/ballot-measures/petitions-circulation | X97: https://www.sos.nd.gov/elections/voter/ballot-measures/measures-ballot | Y97: https://sos.nd.gov/news | AA97: Pass 1 | AB97: 46319
A98: P097 | B98: Ohio | C98: Great Lakes | D98: Statewide | E98: Ohio Equal Rights – Equal Protections amendment and Right to Marry amendment (moved to Nov 2027) | F98: (1) Bar state and local laws that discriminate based on protected traits incl. sexual orientation and gender identity; (2) repeal the constitutional definition of marriage | G98: Two initiated constitutional amendments (split by the Ohio Ballot Board in 2025) | H98: Ohio Equal Rights (executive co-chair Lis Regula) | I98: unknown | J98: Active – paid unconfirmed | K98: Sources conflict: 442,958 valid per amendment (The Buckeye Flame) vs ~413,487 (Daily Signal); plus signatures from at least 44 of 88 counties | L98: July 1, 2027 per The Buckeye Flame's description of the rule (for the Nov 2027 ballot); exact date not officially confirmed here | M98: 46569 | N98: =IF(M98="","",M98-'Read Me'!$B$30) -> 250 | O98: unknown (group declined to say); signatures collected so far carry over | P98: unknown | Q98: unknown | R98: unknown | S98: Lis Regula (executive co-chair) | T98: unknown (website has a collaboration form) | U98: https://ohioequalrights.org | V98: June 17, 2026: OER moved to the 2027 ballot; collection continues. Coverage describes volunteer collection at Pride events. No paid vendor found. Needs ~830k-890k valid signatures across two petitions, so a paid program may be needed to finish. A strong target for a pitch. | W98: https://thebuckeyeflame.com/2026/06/17/organizers-postpone-ohio-equal-rights-ballot-initiatives-to-2027/ | X98: https://www.dailysignal.com/2026/06/29/ohio-amendments-nov-2027/ | Y98: https://www.yahoo.com/news/articles/ohio-voters-could-decide-property-065823650.html | AA98: Pass 1 | AB98: 46319
A99: P098 | B99: Ohio | C99: Great Lakes | D99: Statewide | E99: Committee to Abolish Ohio Property Taxes (moved to Nov 2027) | F99: Constitutional amendment banning taxes on real property (utilities excepted) | G99: Initiated constitutional amendment | H99: Official Committee to Abolish Ohio's Property Taxes (leader Brian Massie) | I99: unknown | J99: Active – paid unconfirmed | K99: 413,488 valid (legal minimum cited by Signal Cleveland); group's own goal 620,000+ | L99: unknown exact date (2027 cycle) | N99: =IF(M99="","",M99-'Read Me'!$B$30) | O99: ~320,000 as of April 2026 announcement (an April 23 report cited 305,000); current count not disclosed | P99: unknown | Q99: unknown | R99: unknown | S99: Brian Massie | T99: unknown | U99: unknown | V99: Dropped its 2026 bid in June 2026 and is targeting Nov 2027; signatures carry over. No source says whether circulators are paid. Opposed by Ohioans to Protect Public Services (protectpublicservices.org). | W99: https://signalcleveland.org/ohio-property-tax-amendment-abolish-ends-2026-ballot-bid-targets-2027-election/ | X99: https://signalcleveland.org/ohio-property-tax-abolition-campaign-hits-305000-signatures-heres-what-that-means-for-its-chances/ | Y99: https://www.wosu.org/2026-06-05/amendment-to-abolish-ohio-property-taxes-wont-be-on-fall-ballot | Z99: https://highlandcountypress.com/news/property-tax-petition-quest-ohio-ballot-pushed-2027 | AA99: Pass 1 | AB99: 46319
A100: P099 | B100: Ohio | C100: Great Lakes | D100: Statewide | E100: Ohioans for Cannabis Choice – SB 56 referendum | F100: Referendum to block SB 56 (hemp/THC restrictions and marijuana law changes) | G100: Statutory referendum | H100: Ohioans for Cannabis Choice | I100: Arno Petition Consultant (California; Michael Arno) as lead; L&R Political Consultants (Larry Laws) recruited; subcontractor Ohio Petitioning Partners (Pam Lauter) | J100: Completed/Expired | K100: 248,092 valid plus 3% of gubernatorial turnout in 44 of 88 counties | L100: March 19, 2026 | M100: 46100 | N100: =IF(M100="","",M100-'Read Me'!$B$30) -> -219 | O100: ~208,000 (per Mark Fashian); failed | P100: $9 per valid signature (reported promise) | Q100: unknown | R100: No more than $100,000 on petitioner payments (per Larry Laws) | S100: unknown | T100: unknown | U100: unknown | V100: Confirmed paid drive. Paid petitioners were pulled Feb 25, 2026, and several say they were never paid (demand letter Mar 27, 2026). A warning sign about vendor payment risk in Ohio. | W100: https://ohiocapitaljournal.com/?p=38817 | X100: https://www.fox19.com/2026/03/18/massive-overhaul-ohio-cannabis-laws-way-after-group-fails-stop-sb-56 | AA100: Pass 1 | AB100: 46319
...

Sheet Active Opportunities
A1: Ranked Opportunities — live and near-live projects
A2: Each project gets 0–5 points on the five ranking rules. Total is a formula. Scoring: Hiring = 5 with a live job link, 2 if a firm is named. Pay = 5 if a dollar rate is published. Urgency = 5 if deadline ≤45 days, 4 ≤90, 3 ≤180, 2 ≤400, 1 unknown. Scale = signatures required (5 ≥300k, 4 ≥70k, 3 statewide/≥20k, 2 local, 1 unknown). Evidence = 5 confirmed, 4 strong, 2 unconfirmed, 1 upcoming.
A4: Rank | B4: State | C4: Campaign / Petition | D4: Status | E4: Circulation Firm | F4: Circulator Pay | G4: Deadline | H4: Signatures Required | I4: Hiring Link | J4: Hiring | K4: Pay | L4: Urgency | M4: Scale | N4: Evidence | O4: TOTAL (0–25) | P4: Why it matters
A5: 1 | B5: Maine | C5: An Act to Amend the Cannabis Legalization Act and the Maine Medical Use of Cannabis Act | D5: Strong evidence active paid | E5: unknown. Out-of-state paid circulators were reported | F5: $1 per signature (one circulator, in a recording reported Jan 2026) | G5: June 8, 2027 filing deadline (for a 2027 election); Feb 2, 2026 was the 2026 cutoff | H5: 67,682 valid | I5: unknown | J5: 2 | K5: 5 | L5: 2 | M5: 3 | N5: 4 | O5: =SUM(J5:N5) -> 16 | P5: Approved for circulation Dec 8, 2025. In Jan 2026, Secretary Bellows testified that circulators were 'people for hire' shipped in from out of state. A Texas circulator said he was paid $1 per signature. The SOS page still lists it as current, with a June 8, 2027 deadline. Not verified whether signatures were filed for 2026 or whether paid collection continues in Oct 2026.
A6: 2 | B6: Florida | C6: Florida Decides Healthcare - Medicaid expansion (2028) | D6: Active – paid unconfirmed | E6: unknown for 2028. For the 2026 drive, The Outreach Team posted paid 'Petitioner' jobs (posted April 8, 2025). | F6: 2026 drive (The Outreach Team, April 2025 posting): $19/hr for circulators, $21-25/hr for leadership, +$1/hr bilingual. The 2028 rate is unknown. | G6: Feb 1, 2028 (standard Florida deadline for the 2028 ballot; not separately confirmed in sources) | H6: 880,062 was the 2026-cycle requirement (8% of voters). The exact 2028 figure is unknown. | I6: https://careers.arena.run/companies/the-outreach-team-2/jobs/48573140-petitioner-help-expand-medicaid-in-florida (2025 posting for the 2026 drive; current status unknown) | J6: 5 | K6: 5 | L6: 1 | M6: 3 | N6: 2 | O6: =SUM(J6:N6) -> 16 | P6: Relaunched signature collection for 2028 on Feb 1, 2026. The new model is mail-in petitions (prepaid return envelope) requested through the website, plus 100+ grassroots partners; that model points away from paid field circulation. Brevard's monthly valid count is small (7 in September 2026), which points to low field activity. The group says HB 1205 'dramatically increased petition costs.' It was lead plaintiff in Florida Decides Healthcare v. Byrd. On April 30, 2026, Judge Walker upheld the circulator registration requirement, the out-of-state and non-citizen circulator bans, felon restrictions, the $50,000-per-violation fine and the felony for filling in petition information. Ballot Access News reported the plaintiffs did not plan to appeal (BAN's May 1 post said the ruling would be appealed, so these conflict). The Florida DOS initiative database (constitutionalinitiatives.dos.fl.gov) was blocked by Cloudflare and could not be checked directly.
A7: 3 | B7: California | C7: Urban Signers LLC - Signature Collector (unnamed petition projects) | D7: Active – paid unconfirmed | E7: Urban Signers LLC | F7: $5 or $10 per signature depending on project; advertised $200-$1,000/day; paid weekly or bi-weekly | G7: unknown | H7: unknown | I7: https://urban-signers-llc.careerplug.com/jobs/3365854 | J7: 5 | K7: 5 | L7: 1 | M7: 1 | N7: 2 | O7: =SUM(J7:N7) -> 14 | P7: Paid job ad; page metadata updated 2026-10-16 (original post date unknown). Names no specific petition, and the only statewide CA petition circulating is the top-two repeal, so which projects are active is unverified.
A8: 4 | B8: Massachusetts | C8: SignatureDrive.com 'speculative' 2028 petitions (incl. 26-06 legislative employee bargaining and 26-12 end gas tax) | D8: Active – paid unconfirmed | E8: SignatureDrive.com (Harold Hubschman) is the filer and would be the firm | F8: unknown | G8: Nov 18, 2026 to local clerks; Dec 2, 2026 to Secretary of State | H8: 74,574 each | I8: unknown | J8: 2 | K8: 0 | L8: 5 | M8: 4 | N8: 2 | O8: =SUM(J8:N8) -> 13 | P8: The Globe names only 2 of the 10 topics; which certified numbers are Hubschman's beyond 26-06 and 26-12 is unverified. With no paying client as of Sept 22, 2026, these may not circulate at scale.
A9: 5 | B9: Massachusetts | C9: Other AG-certified 2028 petitions: 26-01, 26-05, 26-09, 26-10, 26-11, 26-14, 26-15, 26-16, 26-17, 26-18 | D9: Active – paid unconfirmed | E9: SignatureDrive.com (Hubschman's firm) would be the natural vendor, but it is not confirmed collecting on these | F9: unknown | G9: Nov 18, 2026 to local election officials; Dec 2, 2026 to Secretary of the Commonwealth | H9: 74,574 each (first round) | I9: unknown | J9: 2 | K9: 0 | L9: 5 | M9: 4 | N9: 2 | O9: =SUM(J9:N9) -> 13 | P9: A signature-firm owner filed these as products he can pitch to funders. 26-07 and 26-13 were filed but not certified. Any of the 10 could become a paid drive if a funder buys in before Nov 18. These are prime prospects for a petition-management pitch: the measures are certified but have no client yet.
A10: 6 | B10: Louisiana | C10: Recall of Gov. Jeff Landry (and AG Liz Murrill) | D10: Active – paid unconfirmed | E10: unknown | F10: unknown | G10: October 31 2026 (180 days from May 4 2026) | H10: 500,884 | I10: unknown | J10: 0 | K10: 0 | L10: 5 | M10: 5 | N10: 2 | O10: =SUM(J10:N10) -> 12 | P10: Petition began May 4 2026; deadline 7 days away. Appears volunteer-driven (fixed signing sites); no paid circulator evidence. Signature count not reported.
A11: 7 | B11: Massachusetts | C11: Initiative Petition 26-08: data center regulation (2028 ballot) | D11: Active – paid unconfirmed | E11: unknown. Boston.com reports Fleming is tied to JEF Associates, which provides certified signatures and ballot-initiative services; not confirmed as the vendor for this drive | F11: unknown | G11: Nov 18, 2026 to local election officials; Dec 2, 2026 to Secretary of the Commonwealth | H11: 74,574 (first round); about 12,500 more if the Legislature does not act | I11: unknown | J11: 2 | K11: 0 | L11: 5 | M11: 3 | N11: 2 | O11: =SUM(J11:N11) -> 12 | P11: Certified per Foley Hoag. Ballotpedia calls it the nation's second statewide data-center measure. There is no evidence of funding or paid circulation. Possible prospect: environmental or anti-data-center groups would be natural funders.
A12: 8 | B12: New York | C12: 2027 candidate designating and independent nominating petitions (NYC Council, local offices) | D12: Upcoming | E12: unknown | F12: unknown for 2027. Benchmark: Green Party of NY paid $25/hr in 2024 (5 weeks) | G12: unknown — the 2027 NYS political calendar was not found; the brief's estimate is that petitioning starts around late Feb 2027 | H12: Per NY Election Law 6-136 by office (not verified for 2027) | I12: unknown | J12: 0 | K12: 5 | L12: 1 | M12: 5 | N12: 1 | O12: =SUM(J12:N12) -> 12 | P12: No 2027 calendar or 2027 job ads verified. NY has no statewide citizen initiative. The paid-petitioning market is candidate ballot access, concentrated Feb-Apr. Bills S6996/A1223 (2025) affecting petitioning exist, but their content was not verified.
A13: 9 | B13: California | C13: Repeal Top-Two Open Primary (SOS #2022 / AG 26-0004) | D13: Active – paid unconfirmed | E13: unknown | F13: unknown | G13: 2027-01-11 (end of 180-day circulation period; submit to county elections officials) | H13: 874,641 valid | I13: unknown | J13: 0 | K13: 0 | L13: 4 | M13: 5 | N13: 2 | O13: =SUM(J13:N13) -> 11 | P13: Only CA statewide initiative still in circulation (cleared 7/14/26, deadline 1/11/27). Needing ~875k valid signatures in 180 days normally implies paid circulation, but no source found confirming a firm, pay rate or committee spending. Check Cal-Access for the committee's payments to petition firms. No 25% report filed as of check.
A14: 10 | B14: Massachusetts | C14: Initiatives 26-01 (non-ionizing radiation office) and 26-18 (lifetime license-revocation hardship waiver) (2028) | D14: Active – paid unconfirmed | E14: unknown | F14: unknown | G14: Nov 18, 2026 to local election officials; Dec 2, 2026 to Secretary of the Commonwealth | H14: 74,574 each (first round) | I14: unknown | J14: 0 | K14: 0 | L14: 5 | M14: 4 | N14: 2 | O14: =SUM(J14:N14) -> 11 | P14: Both were filed by individuals and certified. No evidence of funding, a committee or paid circulators. Probably volunteer-only or dormant (inference). Low-probability prospects.
A15: 11 | B15: California | C15: Exempts Additional Food Products from State and Local Sales Taxes (SOS #2023 / AG 26-0005) | D15: Active – paid unconfirmed | E15: unknown | F15: unknown | G15: 2027-03-24 | H15: 874,641 valid | I15: unknown | J15: 0 | K15: 0 | L15: 3 | M15: 5 | N15: 2 | O15: =SUM(J15:N15) -> 10 | P15: Entered circulation Sept 25, 2026. It is the newest CA statewide initiative in circulation, per the SOS 2026 release index. No funding committee, firm or signature drive activity was found. A proponent with no visible funding is a possible client for a feasibility or full-campaign pitch.
A16: 12 | B16: Illinois | C16: April 6, 2027 Consolidated Election – nonpartisan/independent nominating petitions and local referenda petitions | D16: Active – paid unconfirmed | E16: unknown | F16: unknown | G16: Nominating papers filed Nov 16–23, 2026; petitions to create a political subdivision due Dec 7, 2026; local public-policy referenda petitions due Jan 4, 2027; party caucus certificates Dec 14–21, 2026 | H16: Varies by office and unit (unknown) | I16: unknown | J16: 0 | K16: 0 | L16: 5 | M16: 3 | N16: 2 | O16: =SUM(J16:N16) -> 10 | P16: Circulation opened Aug 25, 2026. This is the live Illinois petition window, with referendum petitions due Jan 4, 2027. I found no specific paid local referendum drive. This is a calendar opportunity, not a confirmed paid project.
... A49: 45 | B49: District of Columbia | C49: Initiative 88: Rent Control and Housing Eligibility Adjustment Amendment Act of 2026 (rent freeze) | D49: Upcoming | E49: unknown | F49: unknown | G49: 180 days from final approval once litigation clears; earliest ballot is the expected spring 2027 special election | H49: About 24,000 valid (5% of registered voters citywide, incl. 5% in 5 of 8 wards) | I49: unknown | J49: 0 | K49: 0 | L49: 1 | M49: 1 | N49: 1 | O49: =SUM(J49:N49) -> 3 | P49: Litigation blocked collection. A challenge led by the DC Building Industry Association coalition was denied as untimely on Sept 16, 2026; an appeal was filed Sept 18. Whether circulation has started is unknown. Opposition (DCBIA, NAR) is well funded, so a well-funded drive is plausible, but that is not confirmed.

Sheet State Coverage
A1: State | B1: Abbr | C1: Confirmed active paid | D1: Strong evidence active paid | E1: Active – paid unconfirmed | F1: Upcoming | G1: Completed/Expired | H1: No verified project | I1: Total Records | J1: Live (first 4) | K1: Coverage Note
A2: Alabama | B2: AL | C2: =COUNTIFS(Database!$B:$B,$A2,Database!$J:$J,"Confirmed active paid") -> 0 | D2: =COUNTIFS(Database!$B:$B,$A2,Database!$J:$J,"Strong evidence active paid") -> 0 | E2: =COUNTIFS(Database!$B:$B,$A2,Database!$J:$J,"Active – paid unconfirmed") -> 0 | F2: =COUNTIFS(Database!$B:$B,$A2,Database!$J:$J,"Upcoming") -> 0 | G2: =COUNTIFS(Database!$B:$B,$A2,Database!$J:$J,"Completed/Expired") -> 0 | H2: =COUNTIFS(Database!$B:$B,$A2,Database!$J:$J,"No verified project") -> 1 | I2: =SUM(C2:H2) -> 1 | J2: =SUM(C2:F2) -> 0 | K2: =IF(I2=0,"Not yet researched",IF(H2>0,"Searched — nothing verified (gap)","")) -> Searched — nothing verified (gap)
A3: Alaska | B3: AK | C3: =COUNTIFS(Database!$B:$B,$A3,Database!$J:$J,"Confirmed active paid") -> 0 | D3: =COUNTIFS(Database!$B:$B,$A3,Database!$J:$J,"Strong evidence active paid") -> 0 | E3: =COUNTIFS(Database!$B:$B,$A3,Database!$J:$J,"Active – paid unconfirmed") -> 0 | F3: =COUNTIFS(Database!$B:$B,$A3,Database!$J:$J,"Upcoming") -> 1 | G3: =COUNTIFS(Database!$B:$B,$A3,Database!$J:$J,"Completed/Expired") -> 2 | H3: =COUNTIFS(Database!$B:$B,$A3,Database!$J:$J,"No verified project") -> 0 | I3: =SUM(C3:H3) -> 3 | J3: =SUM(C3:F3) -> 1 | K3: =IF(I3=0,"Not yet researched",IF(H3>0,"Searched — nothing verified (gap)",""))
A4: Arizona | B4: AZ | C4: =COUNTIFS(Database!$B:$B,$A4,Database!$J:$J,"Confirmed active paid") -> 0 | D4: =COUNTIFS(Database!$B:$B,$A4,Database!$J:$J,"Strong evidence active paid") -> 0 | E4: =COUNTIFS(Database!$B:$B,$A4,Database!$J:$J,"Active – paid unconfirmed") -> 0 | F4: =COUNTIFS(Database!$B:$B,$A4,Database!$J:$J,"Upcoming") -> 0 | G4: =COUNTIFS(Database!$B:$B,$A4,Database!$J:$J,"Completed/Expired") -> 5 | H4: =COUNTIFS(Database!$B:$B,$A4,Database!$J:$J,"No verified project") -> 0 | I4: =SUM(C4:H4) -> 5 | J4: =SUM(C4:F4) -> 0 | K4: =IF(I4=0,"Not yet researched",IF(H4>0,"Searched — nothing verified (gap)",""))
A5: Arkansas | B5: AR | C5: =COUNTIFS(Database!$B:$B,$A5,Database!$J:$J,"Confirmed active paid") -> 0 | D5: =COUNTIFS(Database!$B:$B,$A5,Database!$J:$J,"Strong evidence active paid") -> 0 | E5: =COUNTIFS(Database!$B:$B,$A5,Database!$J:$J,"Active – paid unconfirmed") -> 0 | F5: =COUNTIFS(Database!$B:$B,$A5,Database!$J:$J,"Upcoming") -> 0 | G5: =COUNTIFS(Database!$B:$B,$A5,Database!$J:$J,"Completed/Expired") -> 1 | H5: =COUNTIFS(Database!$B:$B,$A5,Database!$J:$J,"No verified project") -> 0 | I5: =SUM(C5:H5) -> 1 | J5: =SUM(C5:F5) -> 0 | K5: =IF(I5=0,"Not yet researched",IF(H5>0,"Searched — nothing verified (gap)",""))
A6: California | B6: CA | C6: =COUNTIFS(Database!$B:$B,$A6,Database!$J:$J,"Confirmed active paid") -> 0 | D6: =COUNTIFS(Database!$B:$B,$A6,Database!$J:$J,"Strong evidence active paid") -> 0 | E6: =COUNTIFS(Database!$B:$B,$A6,Database!$J:$J,"Active – paid unconfirmed") -> 3 | F6: =COUNTIFS(Database!$B:$B,$A6,Database!$J:$J,"Upcoming") -> 0 | G6: =COUNTIFS(Database!$B:$B,$A6,Database!$J:$J,"Completed/Expired") -> 8 | H6: =COUNTIFS(Database!$B:$B,$A6,Database!$J:$J,"No verified project") -> 0 | I6: =SUM(C6:H6) -> 11 | J6: =SUM(C6:F6) -> 3 | K6: =IF(I6=0,"Not yet researched",IF(H6>0,"Searched — nothing verified (gap)",""))
A7: Colorado | B7: CO | C7: =COUNTIFS(Database!$B:$B,$A7,Database!$J:$J,"Confirmed active paid") -> 0 | D7: =COUNTIFS(Database!$B:$B,$A7,Database!$J:$J,"Strong evidence active paid") -> 0 | E7: =COUNTIFS(Database!$B:$B,$A7,Database!$J:$J,"Active – paid unconfirmed") -> 0 | F7: =COUNTIFS(Database!$B:$B,$A7,Database!$J:$J,"Upcoming") -> 1 | G7: =COUNTIFS(Database!$B:$B,$A7,Database!$J:$J,"Completed/Expired") -> 5 | H7: =COUNTIFS(Database!$B:$B,$A7,Database!$J:$J,"No verified project") -> 0 | I7: =SUM(C7:H7) -> 6 | J7: =SUM(C7:F7) -> 1 | K7: =IF(I7=0,"Not yet researched",IF(H7>0,"Searched — nothing verified (gap)",""))
A8: Connecticut | B8: CT | C8: =COUNTIFS(Database!$B:$B,$A8,Database!$J:$J,"Confirmed active paid") -> 0 | D8: =COUNTIFS(Database!$B:$B,$A8,Database!$J:$J,"Strong evidence active paid") -> 0 | E8: =COUNTIFS(Database!$B:$B,$A8,Database!$J:$J,"Active – paid unconfirmed") -> 0 | F8: =COUNTIFS(Database!$B:$B,$A8,Database!$J:$J,"Upcoming") -> 0 | G8: =COUNTIFS(Database!$B:$B,$A8,Database!$J:$J,"Completed/Expired") -> 0 | H8: =COUNTIFS(Database!$B:$B,$A8,Database!$J:$J,"No verified project") -> 1 | I8: =SUM(C8:H8) -> 1 | J8: =SUM(C8:F8) -> 0 | K8: =IF(I8=0,"Not yet researched",IF(H8>0,"Searched — nothing verified (gap)","")) -> Searched — nothing verified (gap)
A9: Delaware | B9: DE | C9: =COUNTIFS(Database!$B:$B,$A9,Database!$J:$J,"Confirmed active paid") -> 0 | D9: =COUNTIFS(Database!$B:$B,$A9,Database!$J:$J,"Strong evidence active paid") -> 0 | E9: =COUNTIFS(Database!$B:$B,$A9,Database!$J:$J,"Active – paid unconfirmed") -> 0 | F9: =COUNTIFS(Database!$B:$B,$A9,Database!$J:$J,"Upcoming") -> 0 | G9: =COUNTIFS(Database!$B:$B,$A9,Database!$J:$J,"Completed/Expired") -> 0 | H9: =COUNTIFS(Database!$B:$B,$A9,Database!$J:$J,"No verified project") -> 1 | I9: =SUM(C9:H9) -> 1 | J9: =SUM(C9:F9) -> 0 | K9: =IF(I9=0,"Not yet researched",IF(H9>0,"Searched — nothing verified (gap)","")) -> Searched — nothing verified (gap)
A10: District of Columbia | B10: DC | C10: =COUNTIFS(Database!$B:$B,$A10,Database!$J:$J,"Confirmed active paid") -> 0 | D10: =COUNTIFS(Database!$B:$B,$A10,Database!$J:$J,"Strong evidence active paid") -> 0 | E10: =COUNTIFS(Database!$B:$B,$A10,Database!$J:$J,"Active – paid unconfirmed") -> 1 | F10: =COUNTIFS(Database!$B:$B,$A10,Database!$J:$J,"Upcoming") -> 2 | G10: =COUNTIFS(Database!$B:$B,$A10,Database!$J:$J,"Completed/Expired") -> 1 | H10: =COUNTIFS(Database!$B:$B,$A10,Database!$J:$J,"No verified project") -> 0 | I10: =SUM(C10:H10) -> 4 | J10: =SUM(C10:F10) -> 3 | K10: =IF(I10=0,"Not yet researched",IF(H10>0,"Searched — nothing verified (gap)",""))
A11: Florida | B11: FL | C11: =COUNTIFS(Database!$B:$B,$A11,Database!$J:$J,"Confirmed active paid") -> 0 | D11: =COUNTIFS(Database!$B:$B,$A11,Database!$J:$J,"Strong evidence active paid") -> 0 | E11: =COUNTIFS(Database!$B:$B,$A11,Database!$J:$J,"Active – paid unconfirmed") -> 4 | F11: =COUNTIFS(Database!$B:$B,$A11,Database!$J:$J,"Upcoming") -> 2 | G11: =COUNTIFS(Database!$B:$B,$A11,Database!$J:$J,"Completed/Expired") -> 4 | H11: =COUNTIFS(Database!$B:$B,$A11,Database!$J:$J,"No verified project") -> 0 | I11: =SUM(C11:H11) -> 10 | J11: =SUM(C11:F11) -> 6 | K11: =IF(I11=0,"Not yet researched",IF(H11>0,"Searched — nothing verified (gap)",""))
A12: Georgia | B12: GA | C12: =COUNTIFS(Database!$B:$B,$A12,Database!$J:$J,"Confirmed active paid") -> 0 | D12: =COUNTIFS(Database!$B:$B,$A12,Database!$J:$J,"Strong evidence active paid") -> 0 | E12: =COUNTIFS(Database!$B:$B,$A12,Database!$J:$J,"Active – paid unconfirmed") -> 0 | F12: =COUNTIFS(Database!$B:$B,$A12,Database!$J:$J,"Upcoming") -> 0 | G12: =COUNTIFS(Database!$B:$B,$A12,Database!$J:$J,"Completed/Expired") -> 1 | H12: =COUNTIFS(Database!$B:$B,$A12,Database!$J:$J,"No verified project") -> 0 | I12: =SUM(C12:H12) -> 1 | J12: =SUM(C12:F12) -> 0 | K12: =IF(I12=0,"Not yet researched",IF(H12>0,"Searched — nothing verified (gap)",""))
A13: Hawaii | B13: HI | C13: =COUNTIFS(Database!$B:$B,$A13,Database!$J:$J,"Confirmed active paid") -> 0 | D13: =COUNTIFS(Database!$B:$B,$A13,Database!$J:$J,"Strong evidence active paid") -> 0 | E13: =COUNTIFS(Database!$B:$B,$A13,Database!$J:$J,"Active – paid unconfirmed") -> 0 | F13: =COUNTIFS(Database!$B:$B,$A13,Database!$J:$J,"Upcoming") -> 0 | G13: =COUNTIFS(Database!$B:$B,$A13,Database!$J:$J,"Completed/Expired") -> 0 | H13: =COUNTIFS(Database!$B:$B,$A13,Database!$J:$J,"No verified project") -> 1 | I13: =SUM(C13:H13) -> 1 | J13: =SUM(C13:F13) -> 0 | K13: =IF(I13=0,"Not yet researched",IF(H13>0,"Searched — nothing verified (gap)","")) -> Searched — nothing verified (gap)
... A52: Wyoming | B52: WY | C52: =COUNTIFS(Database!$B:$B,$A52,Database!$J:$J,"Confirmed active paid") -> 0 | D52: =COUNTIFS(Database!$B:$B,$A52,Database!$J:$J,"Strong evidence active paid") -> 0 | E52: =COUNTIFS(Database!$B:$B,$A52,Database!$J:$J,"Active – paid unconfirmed") -> 0 | F52: =COUNTIFS(Database!$B:$B,$A52,Database!$J:$J,"Upcoming") -> 0 | G52: =COUNTIFS(Database!$B:$B,$A52,Database!$J:$J,"Completed/Expired") -> 1 | H52: =COUNTIFS(Database!$B:$B,$A52,Database!$J:$J,"No verified project") -> 0 | I52: =SUM(C52:H52) -> 1 | J52: =SUM(C52:F52) -> 0 | K52: =IF(I52=0,"Not yet researched",IF(H52>0,"Searched — nothing verified (gap)",""))
A53: TOTAL | C53: =SUM(C2:C52) -> 0 | D53: =SUM(D2:D52) -> 1 | E53: =SUM(E2:E52) -> 24 | F53: =SUM(F2:F52) -> 20 | G53: =SUM(G2:G52) -> 73 | H53: =SUM(H2:H52) -> 16 | I53: =SUM(I2:I52) -> 134 | J53: =SUM(J2:J52) -> 45

Sheet Firms
A1: Firm | B1: HQ | C1: Website | D1: Public Contact | E1: States Seen | F1: Known Campaigns (2026) | G1: Projects in Database | H1: Recruiting Link | I1: Stated Pay | J1: Notes | K1: Sources
A2: Advanced Micro Targeting | B2: Dallas, TX (per Missouri Independent; not explicitly called HQ) | C2: unknown | D2: unknown | E2: 2024: NV, AZ, AK, OH, MO, MT (Ballotpedia); 2025: MO (congressional-map referendum) | F2: Missouri referendum on the 2025 congressional map (paid $1.1M through Sept 30, 2025); 2024: Make Elections Fair Arizona | G2: =COUNTIF(Database!$I:$I,"*"&"Advanced Micro Targeting"&"*") -> 0 | H2: unknown (ZipRecruiter results for the name returned AMD listings) | I2: 2024 Arizona gatherer said 'I'm making $29 an hour' (KJZZ) | J2: Founder/president Billy Rogers; founded 2007. Paid $1.1M through Sept 30 2025 by People Not Politicians (MO congressional-map referendum); worked 2024 MO abortion-rights and minimum-wage drives. Sued four firms in Nov 2025 alleging poaching of 28 employees. | K2: https://ballotpedia.org/Grassroots; https://missouriindependent.com/2025/11/21/lawsuit-details-alleged-scheme-to-sabotage-referendum-on-gerrymandered-missouri-congressional-map/; https://kjzz.org/content/1875898/meet-people-doing-hard-expensive-work-gathering-signatures-az-ballot-initiatives
A3: Arno Petition Consultants | B3: unknown (916 area code = Sacramento region, CA) | C3: https://apcusa.com | D3: 916-707-7127; info@apcusa.com | E3: unknown | F3: unknown | G3: =COUNTIF(Database!$I:$I,"*"&"Arno Petition Consultants"&"*") -> 0 | H3: unknown | I3: unknown | J3: Services: initiative & referenda management, local initiatives, ballot access, grassroots, GOTV. | K3: https://apcusa.com/
A4: Blitz Canvassing | B4: 10065 E Harvard Ave, Suite 400, Denver, CO 80231 | C4: unknown (email domain blitzcanvassing.com) | D4: (303) 916-2345; info@blitzcanvassing.com; designated agent Jake Zambrano | E4: 2024: CO, MO; Colorado-licensed petition entity (#2025007) | F4: unknown | G4: =COUNTIF(Database!$I:$I,"*"&"Blitz Canvassing"&"*") -> 0 | H4: unknown | I4: unknown | J4: Colorado petition entity license #2025007 (filed 11/13/2025); circulating CO petitions #175, #234, #362, #302, #256. | K4: https://ballotpedia.org/Grassroots; https://www.coloradosos.gov/pubs/elections/petitionEntities/licensees.html; https://www.coloradosos.gov/pubs/elections/petitionEntities/licenses/2025007BlitzCanvassing.pdf; https://coloradosos.gov/pubs/elections/petitionEntities/licensees.html
A5: Campaign & Petition Management LLC | B5: 2719 Sage St, Colorado Springs, CO 80907 | C5: unknown (email domain campaignpetitionmanagement.com) | D5: (720) 299-9088; bryan@campaignpetitionmanagement.com; designated agent Bryan Crumpton | E5: MI; CO (licensed #2026008) | F5: Americans for Citizen Voting (Michigan proof-of-citizenship amendment): paid nearly $3M for 'petition management' | G5: =COUNTIF(Database!$I:$I,"*"&"Campaign & Petition Management"&"*") -> 2 | H5: unknown | I5: unknown | J5: CO license #2026008 (filed 01/31/2026); circulating CO petitions #175, #177, #232. | K5: https://michiganadvance.com/2026/01/21/voters-say-signature-gatherers-often-misrepresent-what-proposals-will-do-nothing-has-changed/; https://www.coloradosos.gov/pubs/elections/petitionEntities/licensees.html; https://www.coloradosos.gov/pubs/elections/petitionEntities/licenses/2026008CampaignPetitionManagementLLC.pdf
A6: Fair Election Fund | B6: unknown | C6: unknown | D6: unknown | E6: unknown | F6: unknown | G6: =COUNTIF(Database!$I:$I,"*"&"Fair Election Fund"&"*") -> 0 | H6: unknown | I6: unknown | J6: No verifiable petition-firm information found.
A7: FieldWorks LLC | B7: 1629 K St NW, Suite 300, Washington, DC 20006 | C7: https://fieldworks.com/ | D7: (202) 667-4400; contact form at https://fieldworks.com/contact-us | E7: 2024: CO, NE, AZ, MO (Ballotpedia) | F7: unknown - the site names no current client campaigns | G7: =COUNTIF(Database!$I:$I,"*"&"FieldWorks"&"*") -> 0 | H7: https://fieldworks.com/jobs/ ; canvassers/petitioners: https://fieldworks.com/canvassers/ ; directors: https://fieldworks.com/directors/ ; invite-only 'Petition DTS Travel Crew': https://fieldworks.com/?p=5722 | I7: Petition DTS Travel Crew: $24/hr, 8-hr shifts, 7 days a week, travel covered, Nov 25 - Dec 4 (state not named, invite-only for former staff, call or text (771) 213-6692). The general jobs page states no pay. | J7: Founded 2001 in DC by Laurie Moskowitz and Susan Blad Seldin. Ballotpedia: 6 initiatives in 2024 at an average of $19.01 cost per required signature (CPRS). Across 32 ballot measures from 2016-2022, committees paid FieldWorks $58.0M. The Nov 25 - Dec 4 travel crew suggests a late-2026 signature push somewhere; the timing fits a Washington initiative to the legislature, but that is unconfirmed. | K7: https://fieldworks.com/; https://fieldworks.com/jobs/; https://fieldworks.com/?p=5722; https://ballotpedia.org/Grassroots; https://ballotpedia.org/Fieldworks
A8: Landslide Political | B8: Salt Lake City, UT | C8: landslidepolitical.com | D8: unknown | E8: 2024: MT, NE; UT (current Indeed canvasser listing) | F8: unknown | G8: =COUNTIF(Database!$I:$I,"*"&"Landslide Political"&"*") -> 2 | H8: https://www.indeed.com/viewjob?jk=7ea42208bd574788 | I8: $25/hr (Canvasser, Salt Lake City, UT; the listing text does not mention petitions) | J8: Founded 2016 as Grassroots Utah Strategies, renamed 2019; operates in 8 states; minority/LGBTQ+ owned. Sued a reproductive-rights group (Nebraska coverage) over unpaid ~$400K in July 2025. | K8: https://ballotpedia.org/Grassroots; https://www.indeed.com/q-signature-gatherer-jobs.html; https://careers.arena.run/companies/landslide-political-2; https://www.1011now.com/2025/07/21/signature-firm-sues-reproductive-rights-group-over-unpaid-400k/
A9: Let the Voters Decide (LTVD) | B9: Florida (described as 'Florida-based', city unknown) | C9: unknown | D9: unknown (spokesman David Leibowitz, 2022) | E9: MO (2025, named as a defendant); 2020 activity listed by Ballotpedia | F9: unknown | G9: =COUNTIF(Database!$I:$I,"*"&"Let the Voters Decide"&"*") -> 0 | H9: unknown | I9: unknown | J9: Sued the Gascon recall committee (Los Angeles) in 2022. | K9: https://missouriindependent.com/2025/11/21/lawsuit-details-alleged-scheme-to-sabotage-referendum-on-gerrymandered-missouri-congressional-map/; https://ballotpedia.org/Grassroots; https://spectrumnews1.com/ca/la-west/politics/2022/07/25/petition-signature-collecting-company-lawsuit-recall-gascon
A10: LMK Strategies | B10: unknown | C10: unknown | D10: unknown | E10: TX | F10: unknown (Dallas; D Magazine listed 4 active Dallas petition drives in Oct 2026, but that page could not be fetched) | G10: =COUNTIF(Database!$I:$I,"*"&"LMK Strategies"&"*") -> 1 | H10: https://www.ziprecruiter.com/c/LMK-Strategies/Job/Signature-Gatherer/-in-Dallas,TX?jid=ec5f5f29d13fd8bd | I10: $38-50/hr (ZipRecruiter); $34.13-50.00/hr (SimplyHired) | J10: No verifiable information found. | K10: https://www.ziprecruiter.com/Jobs/Petition-Signature; https://www.simplyhired.com/search?q=signature+gatherer+jobs
A11: Mobilize Michigan | B11: Michigan (Detroit listing) | C11: unknown | D11: unknown | E11: MI | F11: unnamed progressive ballot initiatives (signature gathering and voter contact) | G11: =COUNTIF(Database!$I:$I,"*"&"Mobilize Michigan"&"*") -> 0 | H11: https://www.ziprecruiter.com/c/Mobilize-Michigan/Job/Field-Manager/-in-Detroit,MI?jid=40e56da15a1ccabe | I11: Field Manager: $60,000-65,000 salary per the description (the header says $5.0K-6.2K/mo) | J11: Re-posted about 21 days before the snapshot (early Oct 2026). Locations include Flint, Grand Rapids, Kalamazoo, Lansing and Marquette. | K11: https://www.ziprecruiter.com/Jobs/Signature-Gathering/-in-Detroit,MI
A12: Other firms named by Ballotpedia, not checked this session | B12: unknown | C12: unknown | D12: unknown | G12: =COUNTIF(Database!$I:$I,"*"&"Other firms named by Ballotpedia"&"*") -> 0 | H12: unknown | I12: unknown | J12: Ballotpedia list: Ballot Access Management (MA 2024, $5.99 CPRS), Kimball Petition Management (CA 2024, $14.18), The Monaco Group, Your Choice Petitions / TDM Strategies / Allstate Petition Management / Voter Science / Collective Voice Solutions (WA 2024, $4.51), Accelevate 2020, Nationwide Ballot Access, Allied Data Services, Axiom Strategies, Vanguard Field Strategies, Ground Organizing, Sign2Vote, Arno Petition Consultants, National Petition Management Inc., Democracy Resources, National Voter Outreach, JSM Inc., Masterson & Wright, Taylor Petition Management, Osprey Field Services, Verified Arkansas LLC. Colorado's 2026 licensed petition entities also include Ballot Access Pros, Groundgame Political Solutions, Northwest Petition Management, QualifyNow, SynergySignatures, Revolution Field Strategies, Rocky Mountain Voter Outreach and Victory in the Field. 'Fair Election Fund', 'Silver Bullet Group', 'Grassroots Targeting' and 'Signature Gathering Services' could not be verified as petition firms with the searches available. | K12: https://ballotpedia.org/Grassroots; https://www.coloradosos.gov/pubs/elections/petitionEntities/licensees.html
A13: PCI Consultants, Inc. | B13: Los Angeles area, CA (hills above Malibu per KUOW 2016; exact address unknown) | C13: unknown | D13: unknown | E13: 2024: AR, FL; CA (with The Monaco Group) | F13: unknown | G13: =COUNTIF(Database!$I:$I,"*"&"PCI Consultants"&"*") -> 0 | H13: unknown | I13: unknown | J13: Led by Angelo Paparella; formerly Progressive Campaigns, Inc. | K13: https://ballotpedia.org/Grassroots; https://www.kuow.org/stories/paying-signatures-used-be-illegal-now-its-making-californian-rich
A14: Petition Partners (AZ Petition Partners LLC) | B14: Phoenix, AZ | C14: unknown | D14: unknown | E14: AZ | F14: unknown; 2024: RFK Jr. presidential ballot access in AZ (~600 circulators) | G14: =COUNTIF(Database!$I:$I,"*"&"Petition Partners"&"*") -> 0 | H14: unknown | I14: Initiative work starts at about $30/hr, with some workers earning about $55/hr. Candidates pay about $13 per signature on average (2024, KJZZ). | J14: Manager Andrew D. Chavez. Charged by AZ AG Oct 2020 (Prop 208 bonuses); AZ Supreme Court June 2023 (Arizona Petition Partners v. Thompson) held bonuses/higher hourly pay for high producers lawful; per-signature pay remains banned in AZ. | K14: https://kjzz.org/content/1875898/meet-people-doing-hard-expensive-work-gathering-signatures-az-ballot-initiatives; https://www.azag.gov/press-release/phoenix-petition-signature-gathering-company-faces-criminal-charges-alleged-illegal; https://ballot-access.org/?p=82419
A15: SignatureDrive.com | B15: Brookline, Massachusetts (owner's residence per the Boston Globe) | C15: https://signaturedrive.com (domain as named in the article; not fetched) | D15: unknown | E15: MA | F15: Public defender union ballot question (>$1M paid); Vote Yes for Water and Nature (part of ~$970K split between two firms); Hubschman filed paperwork for 10 questions for 2028, including legislative staff unionization and gas tax repeal; none had backers as of Sept 22, 2026 | G15: =COUNTIF(Database!$I:$I,"*"&"SignatureDrive.com"&"*") -> 3 | H15: unknown | I15: unknown | J15: No verifiable information found. | K15: https://www.bostonglobe.com/2026/09/22/newsletters/harold-hubschman-ballot-questions-signatures-the-scrum/
A16: Taylor Petition Management LLC | B16: 1069 Glengary Pl, Colorado Springs, CO 80921 | C16: unknown (email domain tpmusa.com) | D16: 360-239-8321; tracy@tpmusa.com; designated agent Tracy Taylor | E16: unknown | F16: unknown | G16: =COUNTIF(Database!$I:$I,"*"&"Taylor Petition Management"&"*") -> 1 | H16: unknown | I16: unknown | J16: CO license #2012001; circulating CO petitions #108-110. ~$500K collected over 8 years in CO; named in Sept 2026 campaign-finance complaint re: Props 134/135. | K16: https://coloradosos.gov/pubs/elections/petitionEntities/files/TaylorPetitionManagement-116.pdf; https://www.coloradopolitics.com/2026/09/22/campaign-finance-complaint-targets-backers-of-transgender-ballot-measures-over-petitions-4/
A17: The Outreach Team | B17: unknown (job listings in CA, MA, TN, WI, FL, AK, OH; Built In Boston has a company profile) | C17: unknown (applications via theoutreachteam.applytojob.com) | D17: unknown (postings give only the application link) | E17: TN; WI; CA; FL; MA; NV; AK; OH | F17: Nashville 'Restore Our Fairgrounds' referendum (posted Jul 17, 2026); Eau Claire and La Crosse, WI municipal Citizens' Advisory Healthcare Action Committee measures (posted Jun 16, 2026); Long Beach, CA parcel-tax initiative for affordable housing (posted May 20, 2026; closed); Florida 'Expand healthcare to 1.4 million Floridians' (Pensacola listing on Idealist; page could not be fetched, date unknown); GOTV field director roles in AK and OH (current) | G17: =COUNTIF(Database!$I:$I,"*"&"The Outreach Team"&"*") -> 5 | H17: https://careers.arena.run/companies/the-outreach-team-2/jobs/86613658-petition-circulator-expand-affordable-housing | I17: Nashville: $22/hr circulator, $24/hr team lead, up to $35/hr with bonuses, +$2/hr bilingual (ZipRecruiter shows $23.50-25.50/hr). Wisconsin: $21/hr circulator, $23/hr lead. Long Beach: $26/hr, $27/hr lead. GOTV field directors: $1.1K-1.5K/wk. | J17: Ran Florida Decides Healthcare circulator hiring (2025): $19/hr circulators, $21-25/hr leaders; Field Director $59,592-$78,000/yr; FL cities Pensacola, Tampa, Miami, Orlando, Jacksonville, Tallahassee, West Palm, Ft Lauderdale. | K17: https://careers.arena.run/companies/the-outreach-team-2/jobs/86613658-petition-circulator-expand-affordable-housing; https://careers.arena.run/companies/the-outreach-team-2/jobs/82850590-community-petitioner; https://careers.arena.run/companies/the-outreach-team-2/jobs/79505515-petition-circulator; https://www.ziprecruiter.com/Jobs/Petition-Signature; https://ballotpedia.org/Grassroots; https://careers.arena.run/companies/the-outreach-team-2/jobs/48573140-petitioner-help-expand-medicaid-in-florida; https://jobs.arena.run/jobs/field-director-recx-ua8s9k-n6-fw-cq-p
A18: Urban Signers | B18: Los Angeles, CA (Hollywood, 90028, per the listing) | C18: unknown | D18: unknown | E18: CA | F18: unknown | G18: =COUNTIF(Database!$I:$I,"*"&"Urban Signers"&"*") -> 1 | H18: https://www.indeed.com/viewjob?jk=23682f688495564a | I18: $200-1,000/day; $5 or $10 per signature depending on project | J18: No verifiable information found. | K18: https://www.indeed.com/q-signature-gatherer-jobs.html; https://www.simplyhired.com/search?q=signature+gatherer+jobs
A19: Victor's Canvassing / Victors Canvassing | B19: unknown (Colorado-licensed #2020014) | C19: unknown | D19: unknown | E19: CO | F19: unknown | G19: =COUNTIF(Database!$I:$I,"*"&"Victor's Canvassing"&"*") -> 0 | H19: unknown | I19: unknown | J19: Ballotpedia 2024: 2 CO initiatives at an average CPRS of $10.87. | K19: https://ballotpedia.org/Grassroots; https://www.coloradosos.gov/pubs/elections/petitionEntities/licensees.html

Sheet Job Postings
A1: State | B1: City | C1: Campaign | D1: Company | E1: Stated Pay | F1: Date Posted | G1: Platform | H1: Link
A2: Texas | B2: Dallas | C2: unknown | D2: LMK Strategies | E2: $38-50/hr (ZipRecruiter); $34.13-50.00/hr (SimplyHired) | F2: ~Oct 21, 2026 ('3d' on SimplyHired; 'New' on ZipRecruiter) | G2: ZipRecruiter / SimplyHired | H2: https://www.ziprecruiter.com/c/LMK-Strategies/Job/Signature-Gatherer/-in-Dallas,TX?jid=ec5f5f29d13fd8bd
A3: California | B3: Los Angeles (Hollywood) | C3: unknown ('depending on the project') | D3: Urban Signers LLC | E3: $200-1,000/day; $5 or $10 per signature | F3: unknown | G3: Indeed / SimplyHired / ZipRecruiter | H3: https://www.indeed.com/viewjob?jk=23682f688495564a
A4: Tennessee | B4: Nashville | C4: Restore Our Fairgrounds referendum | D4: The Outreach Team | E4: $22/hr circulator, $24/hr lead, up to $35/hr with bonuses, +$2 bilingual (ZipRecruiter: $23.50-25.50/hr) | F4: Jul 17, 2026 on Arena; re-posted ~Oct 17, 2026 on ZipRecruiter | G4: Arena / ZipRecruiter | H4: https://careers.arena.run/companies/the-outreach-team-2/jobs/86613658-petition-circulator-expand-affordable-housing
A5: Colorado | B5: Denver | C5: unknown | D5: PS Logistics LLC | E5: $20/hr | F5: re-posted ~Oct 5, 2026 ('19 days ago') | G5: ZipRecruiter | H5: https://www.ziprecruiter.com/c/PS-Logistics-LLC/Job/Petition-Circulator/-in-Denver,CO?jid=d5c1b43da3aeb6f1
A6: Colorado | B6: Windsor | C6: unknown | D6: PS Logistics LLC | E6: $20/hr | F6: unknown | G6: ZipRecruiter | H6: https://www.ziprecruiter.com/c/PS-Logistics-LLC/Job/Petition-Circulator/-in-Windsor,CO?jid=6bcc15bfa6b7542f
A7: Colorado | B7: Denver | C7: Liquor license petitions (door to door) | D7: Oedipus Petitioning LLC | E7: $500-700/wk | F7: unknown | G7: ZipRecruiter | H7: https://www.ziprecruiter.com/c/Oedipus-Petitioning-LLC/Job/Door-to-Door-Liquor-License-Petitioning/-in-Denver,CO?jid=5cb1e0cd48213fde
A8: Michigan | B8: Detroit (also Flint, Grand Rapids, Kalamazoo, Lansing, Marquette) | C8: unnamed progressive ballot initiatives | D8: Mobilize Michigan | E8: $60,000-65,000 salary per the description (header: $5.0K-6.2K/mo) - Field Manager | F8: re-posted ~Oct 3, 2026 ('21 days ago') | G8: ZipRecruiter | H8: https://www.ziprecruiter.com/c/Mobilize-Michigan/Job/Field-Manager/-in-Detroit,MI?jid=40e56da15a1ccabe
A9: Michigan | B9: Detroit / Dearborn | C9: unknown (community outreach representative) | D9: Verdugo Strategies | E9: $20/hr | F9: unknown | G9: ZipRecruiter | H9: https://www.ziprecruiter.com/c/Verdugo-Strategies/Job/Community-Outreach-Representative(MI)/-in-Detroit,MI?jid=4bfb4f23f6f40de6
A10: District of Columbia | B10: Washington | C10: unknown | D10: PTGR Strategies (via Arena) | E10: $19.25-25.75/hr (ZipRecruiter estimate, not stated by the employer) | F10: unknown | G10: ZipRecruiter | H10: https://www.ziprecruiter.com/c/Arena/Job/PTGR-Strategies:-Signature-Collector/-in-Washington,DC?jid=00b6903f80cd9c1a
A11: Utah | B11: Salt Lake City | C11: unknown (canvasser; petitions not mentioned) | D11: Landslide Political | E11: $25/hr | F11: unknown | G11: Indeed | H11: https://www.indeed.com/viewjob?jk=7ea42208bd574788
A12: unknown (FieldWorks 'program state') | B12: assigned by FieldWorks | C12: unknown | D12: FieldWorks | E12: $24/hr, travel covered (invite-only, former staff) | F12: unknown (work dates Nov 25 - Dec 4) | G12: Company career page | H12: https://fieldworks.com/?p=5722
... A16: Washington | B16: unknown | C16: 'Washington ballot initiatives' (per the listing title) | D16: unknown | E16: unknown | F16: unknown | G16: Craigslist (page could not be fetched; found in search results only) | H16: https://www.craigslist.org/view/d/washington-ballot-initiatives-seeking/nc1dfeoPHm8c19ZKLWWJ7V

Sheet Trends & Laws
A1: Topic | B1: Finding | C1: Sources
A2: Per-signature rates, California 2026 | B2: Spring 2026 statewide initiatives paid circulators up to $15 per signature (NYT via Ballot Access News, SF Examiner), with some $7-12. Per an unverified commenter, local petitions paid $20+ and coordinators received $30+ per signature on $15 petitions. One unverified commenter estimated about $125M spent across 9 CA initiatives (~$10 per raw signature). A video of $5-per-signature payments to signers on a billionaire-tax counter-measure triggered a state probe. | C2: https://ballot-access.org/2026/10/20/new-york-times-story-on-paid-petitioners/; https://www.sfexaminer.com/these-masked-men-in-san-francisco-want-one-thing-your-signature/article_90311f74-0179-527a-a2a5-bdb470813ce2.html; https://sfist.com/2026/03/13/group-filmed-paying-5-per-signature-at-sixth-and-mission-on-pro-billionaire-petitions/
A3: National cost benchmarks | B3: Ballotpedia put the 2024 national average at nearly $15 per signature. 2024 average cost per required signature (CPRS) by firm: AMT $24.37, Landslide $24.17, Blitz $20.86, FieldWorks $19.01, PCI $30.85, The Outreach Team $32.16, Victors $10.87, and Washington firms as low as $4.51. | C3: https://ballotpedia.org/Grassroots; https://michiganadvance.com/2026/01/21/voters-say-signature-gatherers-often-misrepresent-what-proposals-will-do-nothing-has-changed/
A4: Hourly pay in states that ban per-signature pay | B4: Current postings run $20-50/hr. Most Outreach Team and PS Logistics roles pay $20-27/hr, LMK Strategies in Dallas pays $34-50/hr, and Arizona 2024 rates ran $25-30/hr, with Petition Partners top workers at about $55/hr. | C4: https://www.ziprecruiter.com/Jobs/Petition-Signature; https://kjzz.org/content/1875898/meet-people-doing-hard-expensive-work-gathering-signatures-az-ballot-initiatives
A5: Massachusetts | B5: There are 9 questions on the Nov 2026 ballot, tied for the most ever. A referendum petition on the Aug 10, 2026 abortion law (Mass. Citizens for Life / Mass. Family Action) is live now: signatures were due to local clerks Oct 23 and are due to the Secretary of State Nov 6. It needs 37,289 signatures for the 2028 ballot and 49,719 to suspend the law. Harold Hubschman filed 10 prospective 2028 questions. A pending bill would ban per-signature pay and require a paid-circulator disclosure. The Aug 2025 filing produced 42 laws for 2026 and 5 constitutional amendments for 2028. By analogy, the 2028 statute cycle should start with filings in Aug 2027 (inference, not verified). | C5: https://www.wbur.org/news/2026/09/04/massachusetts-abortion-law-2028-refendum; https://www.bostonglobe.com/2026/09/22/newsletters/harold-hubschman-ballot-questions-signatures-the-scrum/; https://www.mass.gov/news/ag-campbells-office-receives-47-ballot-initiative-petitions-proposing-42-laws-and-5-constitutional-amendments
A6: Washington | B6: Initiatives to the legislature need 308,911 valid signatures; the state recommends submitting about 390,000. The last cycle's deadline was Jan 2, 2026. Let's Go Washington was weighing the 2026 ballot versus an initiative to the legislature (for 2027) to repeal the 9.9% millionaires' income tax (May 2026). Whether it chose the initiative-to-the-legislature route was not verified. The 'initiative killer' restriction bill died in the legislature in Feb 2026. FieldWorks' Nov 25 - Dec 4 travel crew fits a late-year WA push, but this is unconfirmed. | C6: https://www.komonews.com/news/local/lets-go-washington-girls-sports-fairness-democratic-process-governer-ferguson-what-is-an-initiative-to-the-legislature-and-how-many-are-in-the-works-right-now; https://washingtonstatestandard.com/2026/05/08/lets-go-washington-will-go-for-income-tax-repeal-on-this-years-ballot/; https://washingtonstatestandard.com/2026/02/17/foes-called-it-the-initiative-killer-now-its-dead-in-the-wa-legislature/; https://fieldworks.com/?p=5722
A7: Maine | B7: The 2026 initiative filing deadline was Feb 2, 2026, requiring 67,682 signatures. The next cycle's requirement and deadline were not verified this session. | C7: https://www.maine.gov/sos/elections-voting/peoples-veto-or-citizens-initiative-resources/deadlines-for-current-citizen-initiatives
A8: Florida HB 1205 (2025) | B8: Circulators must be Florida residents and U.S. citizens and must register with the Division of Elections. Felons without restored rights are barred. Organizations face fines up to $50,000 per ineligible circulator, petitions must be turned in within 10 days (down from 30), and filling in missing petition information is a third-degree felony. A July 2025 preliminary ruling was mixed: some non-citizen/non-resident provisions were enjoined per the Floridian Press headline. After a Feb 2026 trial, Judge Mark Walker upheld the law around Apr 30, 2026. Florida Decides Healthcare was considering an appeal and relaunched for 2028. The net effect is to shut out the out-of-state traveling-circulator model and favor local, Florida-resident crews. | C8: https://floridaphoenix.com/2026/04/30/federal-judge-upholds-floridas-citizen-initiative-restrictions/; https://www.newsfromthestates.com/article/federal-ruling-florida-ballot-initiative-restriction-challenge-could-have-national; https://floridaphoenix.com/2025/07/09/federal-judge-issues-mixed-ruling-on-floridas-new-ballot-initiative-law/
A9: Arkansas 2025 laws | B9: SB 102 bans per-signature pay, requires State Police background checks for paid canvassers, expands disqualifying offenses, and requires local canvassers to be U.S. citizens and Arkansas residents. SB 207 requires a verbal or written fraud warning to signers (Class A misdemeanor if skipped). HB 1221 makes signatures expire at the next general election. HB 1222 expands the AG's power to reject measures. All were signed Mar 3, 2025. | C9: https://news.ballotpedia.org/2025/03/03/arkansas-governor-signs-four-bills-revising-initiative-and-referendum-rules-including-signature-gathering-period-ballot-language-approval-and-circulator-requirements/
A10: State circulator rules overview (Ballotpedia, May 2026) | B10: 21 of 26 initiative states have at least one circulator requirement: 10 ban per-signature pay, 6 require residency, 9 require citizenship, and 12 require paid/volunteer disclosure. Arkansas, Florida, Oklahoma and Montana adopted new circulator policies in 2025, and no state adopted one in 2026. FL and OK have rules in all five areas, while MA, MD, MO, OH and WA have none. | C10: https://news.ballotpedia.org/2026/05/21/twenty-one-states-set-at-least-one-requirement-on-ballot-initiative-petition-circulators-2/
A11: Failed or pending restrictions | B11: South Dakota's HB 1087 (a total ban on paid circulators) failed in the House in Jan 2026 over First Amendment concerns (Meyer v. Grant, 1988). The Michigan Senate passed a per-signature pay ban (SB 529 et al.) on Nov 13, 2025, but its fate in the GOP House was uncertain and no enactment was found. Massachusetts has a pending per-signature ban bill. Montana's CI-133, on the Nov 2026 ballot, aims to shield the initiative process from government interference (article not fetched). Utah and Missouri 2025-26 changes were not verified because the search budget ran out. | C11: https://www.yahoo.com/news/articles/bill-ban-paid-petitioning-fails-001941935.html; https://www.michiganpublic.org/politics-government/2025-11-13/senate-approves-ban-on-paying-petition-circulators-by-the-signature; https://www.bostonglobe.com/2026/09/22/newsletters/harold-hubschman-ballot-questions-signatures-the-scrum/; https://helenair.com/news/state-regional/government-politics/elections/article_6da502f9-6b90-42f1-b8ab-2b790414fb2a.html
A12: Industry conflict and fraud scrutiny | B12: AMT v. Let the Voters Decide et al. (worker-poaching, W.D. Mo., Nov 2025) and the Missouri AG probe of AMT. Michigan voters report misrepresentation by gatherers. California has the $5-per-signer video probe. Quality control and compliance are becoming selling points with clients. | C12: https://missouriindependent.com/2025/11/21/lawsuit-details-alleged-scheme-to-sabotage-referendum-on-gerrymandered-missouri-congressional-map/; https://www.votebeat.org/michigan/2026/01/20/petition-signature-gathering-lying-ballot-questions-constitutional-amendments/
A13: Local and municipal petition demand (late 2026) | B13: Municipal drives are active: Nashville fairgrounds referendum, Wisconsin and Michigan city healthcare-committee measures (City Action Michigan; Kalamazoo measure on the Nov 2026 ballot), 4 Dallas drives (Oct 2026, details not retrieved), and Colorado's 75 licensed 2026 petition entities. This supports a local-campaign niche. | C13: https://careers.arena.run/companies/the-outreach-team-2/jobs/86613658-petition-circulator-expand-affordable-housing; https://watershedvoice.com/2026/10/22/a-closer-look-at-kalamazoos-healthcare-proposal-criticized-by-mayor-as-dark-money/; https://www.dmagazine.com/frontburner/2026/10/4-dallas-petition-drives-voters-should-know-about/; https://www.coloradosos.gov/pubs/elections/petitionEntities/licensees.html

Sheet New Discoveries
A1: Monitoring log — add newly found projects here first
A2: Yellow row = example of the expected format; overwrite it. Once a project is verified, copy it to Database and mark 'Moved to Database' = Yes.
A4: Date Found | B4: State | C4: Campaign / Petition | D4: How Found (source type) | E4: Status | F4: Firm | G4: Pay | H4: Deadline | I4: Source Link | J4: Moved to Database?
A5: 2026-11-02 | B5: Massachusetts | C5: (example) Gas tax repeal 2028 | D5: OCPF expenditure report | E5: Strong evidence active paid | F5: unknown | G5: unknown | H5: 2026-11-18 | I5: https://www.ocpf.us | J5: No
